Pipeline execution/src/modules/mux.v
module mux #(parameter width = 32)(
    input [width-1:0] in0, in1,
    input sel,
    output reg [width-1:0] out
);
    always @(*) begin
        out = (sel) ? in1 : in0;
    end
endmodule

Single Cycle/src/alu.v
module alu (
    input [31:0] A,B,
    input [3:0] alu_ctrl,
    output reg [31:0] alu_out,
    output reg zero
);
    always @(*) begin
        case (alu_ctrl)
            4'd0: alu_out = A + B; //Add
            4'd1: alu_out = A - B; // Substract
            4'd2: alu_out = A & B; //AND
            4'd3: alu_out = A | B; // OR
            4'd4: alu_out = A ^ B; // XOR
            4'd5: alu_out = A << B[4:0]; //SLL
            4'd6: alu_out = A >> B[4:0]; //SRL
            4'd7: alu_out = $signed(A) >>> B[4:0]; //SRA
            4'd8: alu_out = $signed(A) < $signed(B) ? 32'b1 :32'b0; //SLT signed
            4'd9: alu_out = (A < B) ? 32'b1 : 32'b0;
            4'd10: alu_out = B; // PASS B (for LUI, if you decide to use ALU)                               
            default: alu_out = A + B;
        endcase
        zero = (alu_out == 32'b0);
    end
endmodule

src/modules/alu_control.v
module alu_control(
    input  [1:0] ALUOp,
    input  [2:0] funct3,
    input        funct7_5,      // instruction[30]
    output reg [3:0] ALUCtrl
);

always @(*) begin
    case (ALUOp)
        2'b00: ALUCtrl = 4'b0000;              // ADD (load/store, auipc)
        2'b01: ALUCtrl = 4'b0001;              // SUB (branches)

        2'b10: begin                           // R / I-type ALU ops
            case ({funct7_5, funct3})
                4'b0_000: ALUCtrl = 4'b0000;   // ADD / ADDI
                4'b1_000: ALUCtrl = 4'b0001;   // SUB
                4'b0_111: ALUCtrl = 4'b0010;   // AND / ANDI
                4'b0_110: ALUCtrl = 4'b0011;   // OR / ORI
                4'b0_100: ALUCtrl = 4'b0100;   // XOR / XORI
                4'b0_001: ALUCtrl = 4'b0101;   // SLL / SLLI
                4'b0_101: ALUCtrl = 4'b0110;   // SRL / SRLI
                4'b1_101: ALUCtrl = 4'b0111;   // SRA / SRAI
                4'b0_010: ALUCtrl = 4'b1000;   // SLT / SLTI
                4'b0_011: ALUCtrl = 4'b1001;   // SLTU / SLTIU
                default:  ALUCtrl = 4'b0000;
            endcase
        end

        2'b11: begin
            // Special ALUOp for LUI (and only LUI)
            ALUCtrl = 4'b1010;                 // PASS B (alu_out = B = imm_out)
        end

        default: ALUCtrl = 4'b0000;
    endcase
end

endmodule

src/imm.v
module imm(
    input  [31:0] instruction,
    output reg [31:0] imm_out
);
    wire [6:0] opcode = instruction[6:0];

    always @(*) begin
        case (opcode)
            // I-type: OP-IMM, LOAD, JALR
            7'b0010011,   // OP-IMM (ADDI, ANDI, ORI, etc.)
            7'b0000011,   // LOAD  (LB, LH, LW, LBU, LHU)
            7'b1100111:   // JALR
                imm_out = {{20{instruction[31]}}, instruction[31:20]};

            // S-type: STORE
            7'b0100011:
                imm_out = {{20{instruction[31]}},
                           instruction[31:25],
                           instruction[11:7]};

            // B-type: BRANCH
            7'b1100011:
                imm_out = {{19{instruction[31]}},
                           instruction[31],       // imm[12]
                           instruction[7],        // imm[11]
                           instruction[30:25],    // imm[10:5]
                           instruction[11:8],     // imm[4:1]
                           1'b0};                 // imm[0]

            // U-type: LUI / AUIPC
            7'b0110111,   // LUI
            7'b0010111:   // AUIPC
                imm_out = {instruction[31:12], 12'b0};

            // J-type: JAL
            7'b1101111:
                imm_out = {{11{instruction[31]}},
                           instruction[31],       // imm[20]
                           instruction[19:12],    // imm[19:12]
                           instruction[20],       // imm[11]
                           instruction[30:21],    // imm[10:1]
                           1'b0};                 // imm[0]

            default:
                imm_out = 32'b0;
        endcase
    end

endmodule

src/control.v
module control(
    input [6:0] opcode,          
    output reg RegWrite,         
    output reg MemRead,          
    output reg MemWrite,         
    output reg MemToReg,        
    output reg ALUSrc,                      
    output reg Branch,                        
    output reg [1:0] ALUOp       
);

    always @(*) begin
        case (opcode)
            7'b0110011:  // R-type 
            begin  {ALUSrc, MemToReg, RegWrite, MemRead, MemWrite, Branch, ALUOp} <= {1'b0, 1'b0, 1'b1, 1'b0, 1'b0, 1'b0, 2'b10};end
            7'b0010011:   // I-type
            begin {ALUSrc, MemToReg, RegWrite, MemRead, MemWrite, Branch, ALUOp} <= {1'b1, 1'b0, 1'b1, 1'b0, 1'b0, 1'b0, 2'b10};end
            7'b0000011:   // Load 
            begin {ALUSrc, MemToReg, RegWrite, MemRead, MemWrite, Branch, ALUOp} <= {1'b1, 1'b1, 1'b1, 1'b1, 1'b0, 1'b0, 2'b00};end
            7'b0100011:   // Store 
            begin {ALUSrc, MemToReg, RegWrite, MemRead, MemWrite, Branch, ALUOp} <= {1'b1, 1'b0, 1'b0, 1'b0, 1'b1, 1'b0, 2'b00};end
            7'b1100011:   // Branch 
            begin {ALUSrc, MemToReg, RegWrite, MemRead, MemWrite, Branch, ALUOp} <= {1'b0, 1'b0, 1'b0, 1'b0, 1'b0, 1'b1, 2'b11};end  
            7'b1101111:   // Jump 
            begin  {ALUSrc, MemToReg, RegWrite, MemRead, MemWrite, Branch, ALUOp} <= {1'b0, 1'b0, 1'b1, 1'b0, 1'b0, 1'b0, 2'b10};end
            7'b0110111:   // LUI
            begin {ALUSrc, MemToReg, RegWrite, MemRead, MemWrite, Branch, ALUOp} <= {1'b1, 1'b0, 1'b1, 1'b0, 1'b0, 1'b0, 2'b11};end
            default: 
            begin {ALUSrc, MemToReg, RegWrite, MemRead, MemWrite, Branch, ALUOp} <= {1'b0, 1'b0, 1'b0, 1'b0, 1'b0, 1'b0, 2'b00};end  
        endcase
    end

endmodule

Single Cycle/rtl/reg_file.v
module reg_file(
    input         clk,
    input         rst,
    input         RegWrite,
    input  [4:0]  Rs1,
    input  [4:0]  Rs2,
    input  [4:0]  Rd,
    input  [31:0] Write_data,
    output [31:0] read_data1,
    output [31:0] read_data2
);

    // 32 registers, each 32-bit
    reg [31:0] Registers [31:0];

    integer i;

    // Optional: initial values (OK for FPGA, not for ASIC)
    initial begin
        Registers[0]  = 32'd0;
        Registers[1]  = 32'd3;
        Registers[2]  = 32'd2;
        Registers[3]  = 32'd12;
        Registers[4]  = 32'd20;
        Registers[5]  = 32'd3;
        Registers[6]  = 32'd44;
        Registers[7]  = 32'd4;
        Registers[8]  = 32'd2;
        Registers[9]  = 32'd1;
        Registers[10] = 32'd23;
        Registers[11] = 32'd4;
        Registers[12] = 32'd90;
        Registers[13] = 32'd10;
        Registers[14] = 32'd20;
        Registers[15] = 32'd30;
        Registers[16] = 32'd40;
        Registers[17] = 32'd50;
        Registers[18] = 32'd60;
        Registers[19] = 32'd70;
        Registers[20] = 32'd80;
        Registers[21] = 32'd80;
        Registers[22] = 32'd90;
        Registers[23] = 32'd70;
        Registers[24] = 32'd60;
        Registers[25] = 32'd65;
        Registers[26] = 32'd4;
        Registers[27] = 32'd32;
        Registers[28] = 32'd12;
        Registers[29] = 32'd34;
        Registers[30] = 32'd5;
        Registers[31] = 32'd10;
    end

    // Synchronous reset + write
    always @(posedge clk) begin
        if (rst) begin
            for (i = 0; i < 32; i = i + 1)
                Registers[i] <= 32'b0;
        end
        else if (RegWrite && (Rd != 5'd0)) begin
            // x0 is read-only zero in RISC-V: ignore writes to x0
            Registers[Rd] <= Write_data;
        end
    end

    // Combinational read ports
    assign read_data1 = (Rs1 == 5'd0) ? 32'b0 : Registers[Rs1];
    assign read_data2 = (Rs2 == 5'd0) ? 32'b0 : Registers[Rs2];

endmodule

Single Cycle/src/inst_mem.v
module inst_mem(
    input  [31:0] read_address,   // PC (byte address)
    output [31:0] instruction_out
);
    reg [31:0] I_Mem [0:255];     // 256 instructions

    wire [7:0] word_addr = read_address[9:2];

    assign instruction_out = I_Mem[word_addr];

    initial begin
        $readmemh("instruction.mem", I_Mem);
    end
endmodule

Single Cycle/src/branch_unit.v
module branch_unit (
    input        Branch,           // from control (opcode == 1100011)
    input  [2:0] funct3,           // instr[14:12]
    input  [31:0] rs1_data,        // from regfile
    input  [31:0] rs2_data,        // from regfile
    output       take_branch
);

    reg t;

    assign take_branch = t;

    always @(*) begin
        t = 1'b0;  // default: no branch

        if (Branch) begin
            case (funct3)
                3'b000: t = (rs1_data == rs2_data);                         // BEQ
                3'b001: t = (rs1_data != rs2_data);                         // BNE
                3'b100: t = ($signed(rs1_data) <  $signed(rs2_data));       // BLT
                3'b101: t = ($signed(rs1_data) >= $signed(rs2_data));       // BGE
                3'b110: t = (rs1_data < rs2_data);                          // BLTU
                3'b111: t = (rs1_data >= rs2_data);                         // BGEU
                default: t = 1'b0;
            endcase
        end
    end
endmodule

Single Cycle/rtl/adder.v
module adder #(
    parameter WIDTH = 32
)(
    input  [WIDTH-1:0] a,
    input  [WIDTH-1:0] b,
    output [WIDTH-1:0] sum
);
    assign sum = a + b;
endmodule

Single Cycle/rtl/pc.v
module pc (
    input         clk,
    input         rst,
    input  [31:0] pc_in,
    output reg [31:0] pc_out
);
    always @(posedge clk) begin
        if (rst)
            pc_out <= 32'b0;
        else
            pc_out <= pc_in;
    end
endmodule

Single Cycle/src/core_sc.v
module core_sc (
    input clk,
    input rst
);

    // PC and instruction path
    wire [31:0] pc_curr;
    wire [31:0] pc_next;
    wire [31:0] pc_plus4;
    wire [31:0] pc_branch;
    wire [31:0] instr;

    // Register file
    wire [31:0] rs1_data;
    wire [31:0] rs2_data;

    // Immediate
    wire [31:0] imm_out;

    // Control signals
    wire        RegWrite;
    wire        MemRead;
    wire        MemWrite;
    wire        MemToReg;
    wire        ALUSrc;
    wire        Branch;
    wire [1:0]  ALUOp;

    // ALU and ALU control
    wire [3:0]  alu_ctrl;
    wire [31:0] alu_b_in;
    wire [31:0] alu_out;
    wire        zero;

    // Data memory and writeback
    wire [31:0] mem_read_data;
    wire [31:0] wb_data;

    // ------------------------
    // Program counter
    // ------------------------

    pc u_pc (
        .pc_in(pc_next),
        .clk(clk),
        .rst(rst),
        .pc_out(pc_curr)
    );

    // PC + 4
    adder #(.WIDTH(32)) u_pc_plus4 (
        .a(pc_curr),
        .b(32'd4),
        .sum(pc_plus4)
    );

    // Branch target = PC + imm
    adder #(.WIDTH(32)) u_branch_adder (
        .a(pc_curr),
        .b(imm_out),
        .sum(pc_branch)
    );
    
    /*
    // Branch decision (old)
    wire take_branch = Branch & zero;
    */
    // ------------------------
    // Branch block (updated)
    // ------------------------
    /*
    wire [31:0] instr;         // from inst_mem
    wire [31:0] rs1_data;      // from regfile
    wire [31:0] rs2_data;      // from regfile
    wire        Branch;        // from control
    wire        take_branch;
    */
    branch_unit u_branch (
        .Branch     (Branch),
        .funct3     (instr[14:12]),
        .rs1_data   (rs1_data),
        .rs2_data   (rs2_data),
        .take_branch(take_branch)
    );

    // Next PC MUX: sequential or branch target
    mux #(.width(32)) u_pc_mux (
        .in0(pc_plus4),
        .in1(pc_branch),
        .sel(take_branch),
        .out(pc_next)
    );

    // ------------------------
    // Instruction fetch
    // ------------------------

    inst_mem u_imem (
        .read_address(pc_curr),
        .instruction_out(instr)
    );

    // ------------------------
    // Decode fields
    // ------------------------

    wire [6:0] opcode   = instr[6:0];
    wire [4:0] rd       = instr[11:7];
    wire [2:0] funct3   = instr[14:12];
    wire [4:0] rs1      = instr[19:15];
    wire [4:0] rs2      = instr[24:20];
    wire       funct7_5 = instr[30];

    // ------------------------
    // Register file
    // ------------------------

    reg_file u_regfile (
        .clk(clk),
        .rst(rst),
        .RegWrite(RegWrite),
        .Rs1(rs1),
        .Rs2(rs2),
        .Rd(rd),
        .Write_data(wb_data),
        .read_data1(rs1_data),
        .read_data2(rs2_data)
    );

    // ------------------------
    // Main control
    // ------------------------

    control u_ctrl (
        .opcode(opcode),
        .RegWrite(RegWrite),
        .MemRead(MemRead),
        .MemWrite(MemWrite),
        .MemToReg(MemToReg),
        .ALUSrc(ALUSrc),
        .Branch(Branch),
        .ALUOp(ALUOp)
    );

    // ------------------------
    // Immediate generator
    // ------------------------

    imm u_imm (
        .instruction(instr),
        .imm_out(imm_out)
    );

    // ------------------------
    // ALU control
    // ------------------------

    alu_control u_alu_ctrl (
        .ALUOp(ALUOp),
        .funct3(funct3),
        .funct7_5(funct7_5),
        .ALUCtrl(alu_ctrl)
    );

    // ------------------------
    // ALU input B MUX (reg or imm)
    // ------------------------

    mux #(.width(32)) u_alusrc_mux (
        .in0(rs2_data),
        .in1(imm_out),
        .sel(ALUSrc),
        .out(alu_b_in)
    );
    

// PC mux
assign pc_next = take_branch ? pc_branch : pc_plus4;



    // ------------------------
    // ALU
    // ------------------------

    alu u_alu (
        .A(rs1_data),
        .B(alu_b_in),
        .alu_ctrl(alu_ctrl),
        .alu_out(alu_out),
        .zero(zero)
    );

    // ------------------------
    // Simple data memory (word addressed like instruction memory)
    // ------------------------

    reg [31:0] data_mem [0:255];
    wire [7:0] data_word_addr = alu_out[9:2];

    // Combinational read
    assign mem_read_data = data_mem[data_word_addr];

    // Write on store
    integer i;
    always @(posedge clk) begin
        if (rst) begin
            for (i = 0; i < 256; i = i + 1)
                data_mem[i] <= 32'b0;
        end else if (MemWrite) begin
            data_mem[data_word_addr] <= rs2_data;
        end
    end

    // ------------------------
    // Writeback MUX: ALU result or load data
    // ------------------------

    mux #(.width(32)) u_wb_mux (
        .in0(alu_out),
        .in1(mem_read_data),
        .sel(MemToReg),
        .out(wb_data)
    );

endmodule

Pipeline execution/tb/tb_1/core_sc_tb.v
`timescale 1ns/1ns
`include "../../src/core_sc.v"
`include "../../src/adder.v"
`include "../../src/alu_control.v"
`include "../../src/alu.v"
`include "../../src/control.v"
`include "../../src/imm.v"
`include "../../src/inst_mem.v"
`include "../../src/mux.v"
`include "../../src/pc.v"
`include "../../src/reg_file.v"
`include "../../src/branch_unit.v"


module core_sc_tb;

    reg clk;
    reg rst;

    core_sc uut (
        .clk(clk),
        .rst(rst)
    );

    // Clock
    initial begin
        clk = 1'b0;
        forever #10 clk = ~clk;   // 50 MHz
    end

    // Reset and run
    initial begin
        rst = 1'b1;
        #50;
        rst = 1'b0;

        // Run for some cycles
        #1000;
        $finish;
    end

    // Waveform
    initial begin
        $dumpfile("core_sc_waveform.vcd");
        $dumpvars(0, core_sc_tb);
    end

endmodule

Pipeline execution/tb/tb_2/core_sc_waveform.vcd
$date
	Mon Dec 01 21:38:31 2025
$end
$version
	Icarus Verilog
$end
$timescale
	1ns
$end
$scope module core_sc_tb $end
$var reg 1 ! clk $end
$var reg 1 " rst $end
$scope module uut $end
$var wire 2 # ALUOp [1:0] $end
$var wire 1 $ ALUSrc $end
$var wire 1 % Branch $end
$var wire 1 & MemRead $end
$var wire 1 ' MemToReg $end
$var wire 1 ( MemWrite $end
$var wire 1 ) RegWrite $end
$var wire 32 * alu_b_in [31:0] $end
$var wire 4 + alu_ctrl [3:0] $end
$var wire 32 , alu_out [31:0] $end
$var wire 1 - clk $end
$var wire 8 . data_word_addr [7:0] $end
$var wire 3 / funct3 [2:0] $end
$var wire 1 0 funct7_5 $end
$var wire 32 1 imm_out [31:0] $end
$var wire 32 2 instr [31:0] $end
$var wire 32 3 mem_read_data [31:0] $end
$var wire 7 4 opcode [6:0] $end
$var wire 32 5 pc_branch [31:0] $end
$var wire 32 6 pc_curr [31:0] $end
$var wire 32 7 pc_next [31:0] $end
$var wire 32 8 pc_plus4 [31:0] $end
$var wire 5 9 rd [4:0] $end
$var wire 5 : rs1 [4:0] $end
$var wire 32 ; rs1_data [31:0] $end
$var wire 5 < rs2 [4:0] $end
$var wire 32 = rs2_data [31:0] $end
$var wire 1 > rst $end
$var wire 1 ? take_branch $end
$var wire 32 @ wb_data [31:0] $end
$var wire 1 A zero $end
$var integer 32 B i [31:0] $end
$scope module u_pc $end
$var wire 1 - clk $end
$var wire 32 C pc_in [31:0] $end
$var wire 1 > rst $end
$var reg 32 D pc_out [31:0] $end
$upscope $end
$scope module u_pc_plus4 $end
$var wire 32 E a [31:0] $end
$var wire 32 F b [31:0] $end
$var wire 32 G sum [31:0] $end
$upscope $end
$scope module u_branch_adder $end
$var wire 32 H a [31:0] $end
$var wire 32 I b [31:0] $end
$var wire 32 J sum [31:0] $end
$upscope $end
$scope module u_branch $end
$var wire 1 % Branch $end
$var wire 3 K funct3 [2:0] $end
$var wire 32 L rs1_data [31:0] $end
$var wire 32 M rs2_data [31:0] $end
$var wire 1 ? take_branch $end
$var reg 1 N t $end
$upscope $end
$scope module u_pc_mux $end
$var wire 32 O in0 [31:0] $end
$var wire 32 P in1 [31:0] $end
$var wire 1 ? sel $end
$var reg 32 Q out [31:0] $end
$upscope $end
$scope module u_imem $end
$var wire 32 R instruction_out [31:0] $end
$var wire 32 S read_address [31:0] $end
$var wire 8 T word_addr [7:0] $end
$upscope $end
$scope module u_regfile $end
$var wire 5 U Rd [4:0] $end
$var wire 1 ) RegWrite $end
$var wire 5 V Rs1 [4:0] $end
$var wire 5 W Rs2 [4:0] $end
$var wire 32 X Write_data [31:0] $end
$var wire 1 - clk $end
$var wire 32 Y read_data1 [31:0] $end
$var wire 32 Z read_data2 [31:0] $end
$var wire 1 > rst $end
$var integer 32 [ i [31:0] $end
$upscope $end
$scope module u_ctrl $end
$var wire 7 \ opcode [6:0] $end
$var reg 2 ] ALUOp [1:0] $end
$var reg 1 ^ ALUSrc $end
$var reg 1 _ Branch $end
$var reg 1 ` MemRead $end
$var reg 1 a MemToReg $end
$var reg 1 b MemWrite $end
$var reg 1 c RegWrite $end
$upscope $end
$scope module u_imm $end
$var wire 32 d instruction [31:0] $end
$var wire 7 e opcode [6:0] $end
$var reg 32 f imm_out [31:0] $end
$upscope $end
$scope module u_alu_ctrl $end
$var wire 2 g ALUOp [1:0] $end
$var wire 3 h funct3 [2:0] $end
$var wire 1 0 funct7_5 $end
$var reg 4 i ALUCtrl [3:0] $end
$upscope $end
$scope module u_alusrc_mux $end
$var wire 32 j in0 [31:0] $end
$var wire 32 k in1 [31:0] $end
$var wire 1 $ sel $end
$var reg 32 l out [31:0] $end
$upscope $end
$scope module u_alu $end
$var wire 32 m A [31:0] $end
$var wire 32 n B [31:0] $end
$var wire 4 o alu_ctrl [3:0] $end
$var reg 32 p alu_out [31:0] $end
$var reg 1 q zero $end
$upscope $end
$scope module u_wb_mux $end
$var wire 32 r in0 [31:0] $end
$var wire 32 s in1 [31:0] $end
$var wire 1 ' sel $end
$var reg 32 t out [31:0] $end
$upscope $end
$upscope $end
$upscope $end
$enddefinitions $end
#0
$dumpvars
bx t
bx s
bx r
xq
bx p
b0 o
bx n
bx m
bx l
b0 k
bx j
b0 i
bx h
b0 g
b0 f
bx e
bx d
0c
0b
0a
0`
0_
0^
b0 ]
bx \
bx [
bx Z
bx Y
bx X
bx W
bx V
bx U
bx T
bx S
bx R
bx Q
bx P
bx O
0N
bx M
bx L
bx K
bx J
b0 I
bx H
bx G
b100 F
bx E
bx D
bx C
bx B
xA
bx @
0?
1>
bx =
bx <
bx ;
bx :
bx 9
bx 8
bx 7
bx 6
bx 5
bx 4
bx 3
bx 2
b0 1
x0
bx /
bx .
0-
bx ,
b0 +
bx *
0)
0(
0'
0&
0%
0$
b0 #
1"
0!
$end
#10
b0 3
b0 s
b1 .
b101 t
b101 @
b101 X
0q
0A
b101 p
b101 ,
b101 r
b101 l
b101 *
b101 n
b101 f
b101 1
b101 I
b101 k
b0 =
b0 M
b0 Z
b0 j
b0 ;
b0 L
b0 Y
b0 m
1^
1$
1c
1)
b10 ]
b10 #
b10 g
b10011 e
00
b101 <
b101 W
b0 :
b0 V
b0 /
b0 h
b1 9
b1 U
b10011 4
b10011 \
b0 K
b100 7
b100 C
b100 Q
b10100000000000010010011 2
b10100000000000010010011 R
b10100000000000010010011 d
b0 T
b0 D
b100 8
b100 G
b100 O
b101 5
b101 J
b101 P
b0 6
b0 E
b0 H
b0 S
b100000 [
b100000000 B
1!
1-
#20
0!
0-
#30
b100000000 B
b100000 [
1!
1-
#40
0!
0-
#50
b0 .
b1 t
b1 @
b1 X
b1 p
b1 ,
b1 r
b101 =
b101 M
b101 Z
b101 j
b1 l
b1 *
b1 n
b1 <
b1 W
b1010 9
b1010 U
b1 f
b1 1
b1 I
b1 k
b1000 Q
b1000 7
b1000 C
b100000000010100010011 2
b100000000010100010011 R
b100000000010100010011 d
b1 T
b100 D
b1000 8
b1000 G
b1000 O
b101 5
b101 J
b101 P
b100 6
b100 E
b100 H
b100 S
1!
1-
0"
0>
#60
0!
0-
#70
b0 t
b0 @
b0 X
1q
1A
b0 p
b0 ,
b0 r
b0 =
b0 M
b0 Z
b0 j
b0 l
b0 *
b0 n
b0 <
b0 W
b11 9
b11 U
b0 f
b0 1
b0 I
b0 k
b1100 Q
b1100 7
b1100 C
b110010011 2
b110010011 R
b110010011 d
b10 T
b1000 D
b1100 8
b1100 G
b1100 O
b1000 5
b1000 J
b1000 P
b1000 6
b1000 E
b1000 H
b1000 S
1!
1-
#80
0!
0-
#90
b1 t
b1 @
b1 X
0q
0A
b1 p
b1 ,
b1 r
b101 =
b101 M
b101 Z
b101 j
b1 l
b1 *
b1 n
b1 <
b1 W
b100 9
b100 U
b1 f
b1 1
b1 I
b1 k
b10000 Q
b10000 7
b10000 C
b100000000001000010011 2
b100000000001000010011 R
b100000000001000010011 d
b11 T
b1100 D
b10000 8
b10000 G
b10000 O
b1101 5
b1101 J
b1101 P
b1100 6
b1100 E
b1100 H
b1100 S
1!
1-
#100
0!
0-
#110
b1 .
b100 t
b100 @
b100 X
b1 i
b1 +
b1 o
b100 p
b100 ,
b100 r
b1 =
b1 M
b1 Z
b1 j
b101 ;
b101 L
b101 Y
b101 m
0^
0$
0c
0)
1_
1%
b1 ]
b1 #
b1 g
b1 l
b1 *
b1 n
b1100011 e
b100 <
b100 W
b1 :
b1 V
b11000 9
b11000 U
b1100011 4
b1100011 \
b111000 f
b111000 1
b111000 I
b111000 k
b10100 Q
b10100 7
b10100 C
b10010000001000110001100011 2
b10010000001000110001100011 R
b10010000001000110001100011 d
b100 T
b10000 D
b10100 8
b10100 G
b10100 O
b1001000 5
b1001000 J
b1001000 P
b10000 6
b10000 E
b10000 H
b10000 S
1!
1-
#120
0!
0-
#130
b0 .
b0 t
b0 @
b0 X
1q
1A
b0 p
b0 ,
b0 r
b0 l
b0 *
b0 n
b0 i
b0 +
b0 o
b0 =
b0 M
b0 Z
b0 j
b0 ;
b0 L
b0 Y
b0 m
1^
1$
1c
1)
0_
0%
b10 ]
b10 #
b10 g
b10011 e
b0 <
b0 W
b0 :
b0 V
b101 9
b101 U
b10011 4
b10011 \
b0 f
b0 1
b0 I
b0 k
b11000 Q
b11000 7
b11000 C
b1010010011 2
b1010010011 R
b1010010011 d
b101 T
b10100 D
b11000 8
b11000 G
b11000 O
b10100 5
b10100 J
b10100 P
b10100 6
b10100 E
b10100 H
b10100 S
1!
1-
#140
0!
0-
#150
b0 .
b1 t
b1 @
b1 X
0q
0A
b1 p
b1 ,
b1 r
b1 =
b1 M
b1 Z
b1 j
0^
0$
b1 l
b1 *
b1 n
b110011 e
b1010 <
b1010 W
b110 9
b110 U
b110011 4
b110011 \
b0 f
b0 1
b0 I
b0 k
b11100 Q
b11100 7
b11100 C
b101000000000001100110011 2
b101000000000001100110011 R
b101000000000001100110011 d
b110 T
b11000 D
b11100 8
b11100 G
b11100 O
b11000 5
b11000 J
b11000 P
b11000 6
b11000 E
b11000 H
b11000 S
1!
1-
#160
0!
0-
#170
b1 f
b1 1
b1 I
b1 k
b101 =
b101 M
b101 Z
b101 j
1^
1$
b10011 e
b1 <
b1 W
b111 9
b111 U
b10011 4
b10011 \
b100000 Q
b100000 7
b100000 C
b100000000001110010011 2
b100000000001110010011 R
b100000000001110010011 d
b111 T
b11100 D
b100000 8
b100000 G
b100000 O
b11101 5
b11101 J
b11101 P
b11100 6
b11100 E
b11100 H
b11100 S
1!
1-
#180
0!
0-
#190
1q
1A
b0 .
b0 t
b0 @
b0 X
1N
1?
b1 i
b1 +
b1 o
b0 p
b0 ,
b0 r
b1 =
b1 M
b1 Z
b1 j
b1 ;
b1 L
b1 Y
b1 m
0^
0$
0c
0)
1_
1%
b1 ]
b1 #
b1 g
b1 l
b1 *
b1 n
b1100011 e
b111 <
b111 W
b111 :
b111 V
b1100 9
b1100 U
b1100011 4
b1100011 \
b1100 f
b1100 1
b1100 I
b1100 k
b101100 Q
b101100 7
b101100 C
b11100111000011001100011 2
b11100111000011001100011 R
b11100111000011001100011 d
b1000 T
b100000 D
b100100 8
b100100 G
b100100 O
b101100 5
b101100 J
b101100 P
b100000 6
b100000 E
b100000 H
b100000 S
1!
1-
#200
0!
0-
#210
b0 .
b0 t
b0 @
b0 X
b0 l
b0 *
b0 n
1q
1A
b0 p
b0 ,
b0 r
1N
1?
b0 =
b0 M
b0 Z
b0 j
b0 ;
b0 L
b0 Y
b0 m
10
b0 <
b0 W
b0 :
b0 V
b11101 9
b11101 U
b11111111111111111111111111111100 f
b11111111111111111111111111111100 1
b11111111111111111111111111111100 I
b11111111111111111111111111111100 k
b101000 Q
b101000 7
b101000 C
b11111110000000000000111011100011 2
b11111110000000000000111011100011 R
b11111110000000000000111011100011 d
b1011 T
b101100 D
b110000 8
b110000 G
b110000 O
b101000 5
b101000 J
b101000 P
b101100 6
b101100 E
b101100 H
b101100 S
1!
1-
#220
0!
0-
#230
b10 t
b10 @
b10 X
0q
0A
b10 p
b10 ,
b10 r
b11111111111111111111111111111111 l
b11111111111111111111111111111111 *
b11111111111111111111111111111111 n
0N
0?
b1 ;
b1 L
b1 Y
b1 m
1^
1$
1c
1)
0_
0%
b10 ]
b10 #
b10 g
b10011 e
b11111 <
b11111 W
b111 :
b111 V
b111 9
b111 U
b10011 4
b10011 \
b11111111111111111111111111111111 f
b11111111111111111111111111111111 1
b11111111111111111111111111111111 I
b11111111111111111111111111111111 k
b101100 Q
b101100 7
b101100 C
b11111111111100111000001110010011 2
b11111111111100111000001110010011 R
b11111111111100111000001110010011 d
b1010 T
b101000 D
b101100 8
b101100 G
b101100 O
b100111 5
b100111 J
b100111 P
b101000 6
b101000 E
b101000 H
b101000 S
1!
1-
#240
0!
0-
#250
1q
1A
b0 .
1N
1?
0^
0$
0c
0)
1_
1%
b1 ]
b1 #
b1 g
b0 l
b0 *
b0 n
b0 t
b0 @
b0 X
b1100011 e
b0 <
b0 W
b0 :
b0 V
b11101 9
b11101 U
b1100011 4
b1100011 \
b11111111111111111111111111111100 f
b11111111111111111111111111111100 1
b11111111111111111111111111111100 I
b11111111111111111111111111111100 k
b0 p
b0 ,
b0 r
b101000 Q
b101000 7
b101000 C
b11111110000000000000111011100011 2
b11111110000000000000111011100011 R
b11111110000000000000111011100011 d
b1011 T
b0 ;
b0 L
b0 Y
b0 m
b101100 D
b110000 8
b110000 G
b110000 O
b101000 5
b101000 J
b101000 P
b101100 6
b101100 E
b101100 H
b101100 S
1!
1-
#260
0!
0-
#270
b11 t
b11 @
b11 X
0q
0A
b11 p
b11 ,
b11 r
b11111111111111111111111111111111 l
b11111111111111111111111111111111 *
b11111111111111111111111111111111 n
0N
0?
b10 ;
b10 L
b10 Y
b10 m
1^
1$
1c
1)
0_
0%
b10 ]
b10 #
b10 g
b10011 e
b11111 <
b11111 W
b111 :
b111 V
b111 9
b111 U
b10011 4
b10011 \
b11111111111111111111111111111111 f
b11111111111111111111111111111111 1
b11111111111111111111111111111111 I
b11111111111111111111111111111111 k
b101100 Q
b101100 7
b101100 C
b11111111111100111000001110010011 2
b11111111111100111000001110010011 R
b11111111111100111000001110010011 d
b1010 T
b101000 D
b101100 8
b101100 G
b101100 O
b100111 5
b100111 J
b100111 P
b101000 6
b101000 E
b101000 H
b101000 S
1!
1-
#280
0!
0-
#290
1q
1A
1N
1?
0^
0$
0c
0)
1_
1%
b1 ]
b1 #
b1 g
b0 l
b0 *
b0 n
b0 .
b0 t
b0 @
b0 X
b1100011 e
b0 <
b0 W
b0 :
b0 V
b11101 9
b11101 U
b1100011 4
b1100011 \
b11111111111111111111111111111100 f
b11111111111111111111111111111100 1
b11111111111111111111111111111100 I
b11111111111111111111111111111100 k
b0 p
b0 ,
b0 r
b101000 Q
b101000 7
b101000 C
b11111110000000000000111011100011 2
b11111110000000000000111011100011 R
b11111110000000000000111011100011 d
b1011 T
b0 ;
b0 L
b0 Y
b0 m
b101100 D
b110000 8
b110000 G
b110000 O
b101000 5
b101000 J
b101000 P
b101100 6
b101100 E
b101100 H
b101100 S
1!
1-
#300
0!
0-
#310
b1 .
b100 t
b100 @
b100 X
0q
0A
b100 p
b100 ,
b100 r
b11111111111111111111111111111111 l
b11111111111111111111111111111111 *
b11111111111111111111111111111111 n
0N
0?
b11 ;
b11 L
b11 Y
b11 m
1^
1$
1c
1)
0_
0%
b10 ]
b10 #
b10 g
b10011 e
b11111 <
b11111 W
b111 :
b111 V
b111 9
b111 U
b10011 4
b10011 \
b11111111111111111111111111111111 f
b11111111111111111111111111111111 1
b11111111111111111111111111111111 I
b11111111111111111111111111111111 k
b101100 Q
b101100 7
b101100 C
b11111111111100111000001110010011 2
b11111111111100111000001110010011 R
b11111111111100111000001110010011 d
b1010 T
b101000 D
b101100 8
b101100 G
b101100 O
b100111 5
b100111 J
b100111 P
b101000 6
b101000 E
b101000 H
b101000 S
1!
1-
#320
0!
0-
