Pipeline execution/src/modules/mux.v
module mux #(parameter width = 32)(
    input [width-1:0] in0, in1,
    input sel,
    output reg [width-1:0] out
);
    always @(*) begin
        out = (sel) ? in1 : in0;
    end
endmodule

Single Cycle/src/alu.v
module alu (
    input [31:0] A,B,
    input [3:0] alu_ctrl,
    output reg [31:0] alu_out,
    output reg zero
);
    always @(*) begin
        case (alu_ctrl)
            4'd0: alu_out = A + B; //Add
            4'd1: alu_out = A - B; // Substract
            4'd2: alu_out = A & B; //AND
            4'd3: alu_out = A | B; // OR
            4'd4: alu_out = A ^ B; // XOR
            4'd5: alu_out = A << B[4:0]; //SLL
            4'd6: alu_out = A >> B[4:0]; //SRL
            4'd7: alu_out = $signed(A) >>> B[4:0]; //SRA
            4'd8: alu_out = $signed(A) < $signed(B) ? 32'b1 :32'b0; //SLT signed
            4'd9: alu_out = (A < B) ? 32'b1 : 32'b0;
            4'd10: alu_out = B; // PASS B (for LUI, if you decide to use ALU)                               
            default: alu_out = A + B;
        endcase
        zero = (alu_out == 32'b0);
    end
endmodule

src/modules/alu_control.v
module alu_control(
    input  [1:0] ALUOp,
    input  [2:0] funct3,
    input        funct7_5,      // instruction[30]
    output reg [3:0] ALUCtrl
);

always @(*) begin
    case (ALUOp)
        2'b00: ALUCtrl = 4'b0000;              // ADD (load/store, auipc)
        2'b01: ALUCtrl = 4'b0001;              // SUB (branches)

        2'b10: begin                           // R / I-type ALU ops
            case ({funct7_5, funct3})
                4'b0_000: ALUCtrl = 4'b0000;   // ADD / ADDI
                4'b1_000: ALUCtrl = 4'b0001;   // SUB
                4'b0_111: ALUCtrl = 4'b0010;   // AND / ANDI
                4'b0_110: ALUCtrl = 4'b0011;   // OR / ORI
                4'b0_100: ALUCtrl = 4'b0100;   // XOR / XORI
                4'b0_001: ALUCtrl = 4'b0101;   // SLL / SLLI
                4'b0_101: ALUCtrl = 4'b0110;   // SRL / SRLI
                4'b1_101: ALUCtrl = 4'b0111;   // SRA / SRAI
                4'b0_010: ALUCtrl = 4'b1000;   // SLT / SLTI
                4'b0_011: ALUCtrl = 4'b1001;   // SLTU / SLTIU
                default:  ALUCtrl = 4'b0000;
            endcase
        end

        2'b11: begin
            // Special ALUOp for LUI (and only LUI)
            ALUCtrl = 4'b1010;                 // PASS B (alu_out = B = imm_out)
        end

        default: ALUCtrl = 4'b0000;
    endcase
end

endmodule

src/imm.v
module imm(
    input  [31:0] instruction,
    output reg [31:0] imm_out
);
    wire [6:0] opcode = instruction[6:0];

    always @(*) begin
        case (opcode)
            // I-type: OP-IMM, LOAD, JALR
            7'b0010011,   // OP-IMM (ADDI, ANDI, ORI, etc.)
            7'b0000011,   // LOAD  (LB, LH, LW, LBU, LHU)
            7'b1100111:   // JALR
                imm_out = {{20{instruction[31]}}, instruction[31:20]};

            // S-type: STORE
            7'b0100011:
                imm_out = {{20{instruction[31]}},
                           instruction[31:25],
                           instruction[11:7]};

            // B-type: BRANCH
            7'b1100011:
                imm_out = {{19{instruction[31]}},
                           instruction[31],       // imm[12]
                           instruction[7],        // imm[11]
                           instruction[30:25],    // imm[10:5]
                           instruction[11:8],     // imm[4:1]
                           1'b0};                 // imm[0]

            // U-type: LUI / AUIPC
            7'b0110111,   // LUI
            7'b0010111:   // AUIPC
                imm_out = {instruction[31:12], 12'b0};

            // J-type: JAL
            7'b1101111:
                imm_out = {{11{instruction[31]}},
                           instruction[31],       // imm[20]
                           instruction[19:12],    // imm[19:12]
                           instruction[20],       // imm[11]
                           instruction[30:21],    // imm[10:1]
                           1'b0};                 // imm[0]

            default:
                imm_out = 32'b0;
        endcase
    end

endmodule

src/control.v
module control(
    input [6:0] opcode,          
    output reg RegWrite,         
    output reg MemRead,          
    output reg MemWrite,         
    output reg MemToReg,        
    output reg ALUSrc,                      
    output reg Branch,                        
    output reg [1:0] ALUOp       
);

    always @(*) begin
        case (opcode)
            7'b0110011:  // R-type 
            begin  {ALUSrc, MemToReg, RegWrite, MemRead, MemWrite, Branch, ALUOp} <= {1'b0, 1'b0, 1'b1, 1'b0, 1'b0, 1'b0, 2'b10};end
            7'b0010011:   // I-type
            begin {ALUSrc, MemToReg, RegWrite, MemRead, MemWrite, Branch, ALUOp} <= {1'b1, 1'b0, 1'b1, 1'b0, 1'b0, 1'b0, 2'b10};end
            7'b0000011:   // Load 
            begin {ALUSrc, MemToReg, RegWrite, MemRead, MemWrite, Branch, ALUOp} <= {1'b1, 1'b1, 1'b1, 1'b1, 1'b0, 1'b0, 2'b00};end
            7'b0100011:   // Store 
            begin {ALUSrc, MemToReg, RegWrite, MemRead, MemWrite, Branch, ALUOp} <= {1'b1, 1'b0, 1'b0, 1'b0, 1'b1, 1'b0, 2'b00};end
            7'b1100011:   // Branch 
            begin {ALUSrc, MemToReg, RegWrite, MemRead, MemWrite, Branch, ALUOp} <= {1'b0, 1'b0, 1'b0, 1'b0, 1'b0, 1'b1, 2'b11};end  
            7'b1101111:   // Jump 
            begin  {ALUSrc, MemToReg, RegWrite, MemRead, MemWrite, Branch, ALUOp} <= {1'b0, 1'b0, 1'b1, 1'b0, 1'b0, 1'b0, 2'b10};end
            7'b0110111:   // LUI
            begin {ALUSrc, MemToReg, RegWrite, MemRead, MemWrite, Branch, ALUOp} <= {1'b1, 1'b0, 1'b1, 1'b0, 1'b0, 1'b0, 2'b11};end
            default: 
            begin {ALUSrc, MemToReg, RegWrite, MemRead, MemWrite, Branch, ALUOp} <= {1'b0, 1'b0, 1'b0, 1'b0, 1'b0, 1'b0, 2'b00};end  
        endcase
    end

endmodule

Single Cycle/rtl/reg_file.v
module reg_file(
    input         clk,
    input         rst,
    input         RegWrite,
    input  [4:0]  Rs1,
    input  [4:0]  Rs2,
    input  [4:0]  Rd,
    input  [31:0] Write_data,
    output [31:0] read_data1,
    output [31:0] read_data2
);

    // 32 registers, each 32-bit
    reg [31:0] Registers [31:0];

    integer i;

    // Optional: initial values (OK for FPGA, not for ASIC)
    initial begin
        Registers[0]  = 32'd0;
        Registers[1]  = 32'd3;
        Registers[2]  = 32'd2;
        Registers[3]  = 32'd12;
        Registers[4]  = 32'd20;
        Registers[5]  = 32'd3;
        Registers[6]  = 32'd44;
        Registers[7]  = 32'd4;
        Registers[8]  = 32'd2;
        Registers[9]  = 32'd1;
        Registers[10] = 32'd23;
        Registers[11] = 32'd4;
        Registers[12] = 32'd90;
        Registers[13] = 32'd10;
        Registers[14] = 32'd20;
        Registers[15] = 32'd30;
        Registers[16] = 32'd40;
        Registers[17] = 32'd50;
        Registers[18] = 32'd60;
        Registers[19] = 32'd70;
        Registers[20] = 32'd80;
        Registers[21] = 32'd80;
        Registers[22] = 32'd90;
        Registers[23] = 32'd70;
        Registers[24] = 32'd60;
        Registers[25] = 32'd65;
        Registers[26] = 32'd4;
        Registers[27] = 32'd32;
        Registers[28] = 32'd12;
        Registers[29] = 32'd34;
        Registers[30] = 32'd5;
        Registers[31] = 32'd10;
    end

    // Synchronous reset + write
    always @(posedge clk) begin
        if (rst) begin
            for (i = 0; i < 32; i = i + 1)
                Registers[i] <= 32'b0;
        end
        else if (RegWrite && (Rd != 5'd0)) begin
            // x0 is read-only zero in RISC-V: ignore writes to x0
            Registers[Rd] <= Write_data;
        end
    end

    // Combinational read ports
    assign read_data1 = (Rs1 == 5'd0) ? 32'b0 : Registers[Rs1];
    assign read_data2 = (Rs2 == 5'd0) ? 32'b0 : Registers[Rs2];

endmodule

Single Cycle/src/inst_mem.v
module inst_mem(
    input  [31:0] read_address,   // PC (byte address)
    output [31:0] instruction_out
);
    reg [31:0] I_Mem [0:255];     // 256 instructions

    wire [7:0] word_addr = read_address[9:2];

    assign instruction_out = I_Mem[word_addr];

    initial begin
        $readmemh("instruction.mem", I_Mem);
    end
endmodule

Single Cycle/src/branch_unit.v
module branch_unit (
    input        Branch,           // from control (opcode == 1100011)
    input  [2:0] funct3,           // instr[14:12]
    input  [31:0] rs1_data,        // from regfile
    input  [31:0] rs2_data,        // from regfile
    output       take_branch
);

    reg t;

    assign take_branch = t;

    always @(*) begin
        t = 1'b0;  // default: no branch

        if (Branch) begin
            case (funct3)
                3'b000: t = (rs1_data == rs2_data);                         // BEQ
                3'b001: t = (rs1_data != rs2_data);                         // BNE
                3'b100: t = ($signed(rs1_data) <  $signed(rs2_data));       // BLT
                3'b101: t = ($signed(rs1_data) >= $signed(rs2_data));       // BGE
                3'b110: t = (rs1_data < rs2_data);                          // BLTU
                3'b111: t = (rs1_data >= rs2_data);                         // BGEU
                default: t = 1'b0;
            endcase
        end
    end
endmodule

Single Cycle/rtl/adder.v
module adder #(
    parameter WIDTH = 32
)(
    input  [WIDTH-1:0] a,
    input  [WIDTH-1:0] b,
    output [WIDTH-1:0] sum
);
    assign sum = a + b;
endmodule

Single Cycle/rtl/pc.v
module pc (
    input         clk,
    input         rst,
    input  [31:0] pc_in,
    output reg [31:0] pc_out
);
    always @(posedge clk) begin
        if (rst)
            pc_out <= 32'b0;
        else
            pc_out <= pc_in;
    end
endmodule

Single Cycle/src/core_sc.v
module core_sc (
    input clk,
    input rst
);

    // PC and instruction path
    wire [31:0] pc_curr;
    wire [31:0] pc_next;
    wire [31:0] pc_plus4;
    wire [31:0] pc_branch;
    wire [31:0] instr;

    // Register file
    wire [31:0] rs1_data;
    wire [31:0] rs2_data;

    // Immediate
    wire [31:0] imm_out;

    // Control signals
    wire        RegWrite;
    wire        MemRead;
    wire        MemWrite;
    wire        MemToReg;
    wire        ALUSrc;
    wire        Branch;
    wire [1:0]  ALUOp;

    // ALU and ALU control
    wire [3:0]  alu_ctrl;
    wire [31:0] alu_b_in;
    wire [31:0] alu_out;
    wire        zero;

    // Data memory and writeback
    wire [31:0] mem_read_data;
    wire [31:0] wb_data;

    // ------------------------
    // Program counter
    // ------------------------

    pc u_pc (
        .pc_in(pc_next),
        .clk(clk),
        .rst(rst),
        .pc_out(pc_curr)
    );

    // PC + 4
    adder #(.WIDTH(32)) u_pc_plus4 (
        .a(pc_curr),
        .b(32'd4),
        .sum(pc_plus4)
    );

    // Branch target = PC + imm
    adder #(.WIDTH(32)) u_branch_adder (
        .a(pc_curr),
        .b(imm_out),
        .sum(pc_branch)
    );
    
    /*
    // Branch decision (old)
    wire take_branch = Branch & zero;
    */
    // ------------------------
    // Branch block (updated)
    // ------------------------
    /*
    wire [31:0] instr;         // from inst_mem
    wire [31:0] rs1_data;      // from regfile
    wire [31:0] rs2_data;      // from regfile
    wire        Branch;        // from control
    wire        take_branch;
    */
    branch_unit u_branch (
        .Branch     (Branch),
        .funct3     (instr[14:12]),
        .rs1_data   (rs1_data),
        .rs2_data   (rs2_data),
        .take_branch(take_branch)
    );

    // Next PC MUX: sequential or branch target
    mux #(.width(32)) u_pc_mux (
        .in0(pc_plus4),
        .in1(pc_branch),
        .sel(take_branch),
        .out(pc_next)
    );

    // ------------------------
    // Instruction fetch
    // ------------------------

    inst_mem u_imem (
        .read_address(pc_curr),
        .instruction_out(instr)
    );

    // ------------------------
    // Decode fields
    // ------------------------

    wire [6:0] opcode   = instr[6:0];
    wire [4:0] rd       = instr[11:7];
    wire [2:0] funct3   = instr[14:12];
    wire [4:0] rs1      = instr[19:15];
    wire [4:0] rs2      = instr[24:20];
    wire       funct7_5 = instr[30];

    // ------------------------
    // Register file
    // ------------------------

    reg_file u_regfile (
        .clk(clk),
        .rst(rst),
        .RegWrite(RegWrite),
        .Rs1(rs1),
        .Rs2(rs2),
        .Rd(rd),
        .Write_data(wb_data),
        .read_data1(rs1_data),
        .read_data2(rs2_data)
    );

    // ------------------------
    // Main control
    // ------------------------

    control u_ctrl (
        .opcode(opcode),
        .RegWrite(RegWrite),
        .MemRead(MemRead),
        .MemWrite(MemWrite),
        .MemToReg(MemToReg),
        .ALUSrc(ALUSrc),
        .Branch(Branch),
        .ALUOp(ALUOp)
    );

    // ------------------------
    // Immediate generator
    // ------------------------

    imm u_imm (
        .instruction(instr),
        .imm_out(imm_out)
    );

    // ------------------------
    // ALU control
    // ------------------------

    alu_control u_alu_ctrl (
        .ALUOp(ALUOp),
        .funct3(funct3),
        .funct7_5(funct7_5),
        .ALUCtrl(alu_ctrl)
    );

    // ------------------------
    // ALU input B MUX (reg or imm)
    // ------------------------

    mux #(.width(32)) u_alusrc_mux (
        .in0(rs2_data),
        .in1(imm_out),
        .sel(ALUSrc),
        .out(alu_b_in)
    );
    

// PC mux
assign pc_next = take_branch ? pc_branch : pc_plus4;



    // ------------------------
    // ALU
    // ------------------------

    alu u_alu (
        .A(rs1_data),
        .B(alu_b_in),
        .alu_ctrl(alu_ctrl),
        .alu_out(alu_out),
        .zero(zero)
    );

    // ------------------------
    // Simple data memory (word addressed like instruction memory)
    // ------------------------

    reg [31:0] data_mem [0:255];
    wire [7:0] data_word_addr = alu_out[9:2];

    // Combinational read
    assign mem_read_data = data_mem[data_word_addr];

    // Write on store
    integer i;
    always @(posedge clk) begin
        if (rst) begin
            for (i = 0; i < 256; i = i + 1)
                data_mem[i] <= 32'b0;
        end else if (MemWrite) begin
            data_mem[data_word_addr] <= rs2_data;
        end
    end

    // ------------------------
    // Writeback MUX: ALU result or load data
    // ------------------------

    mux #(.width(32)) u_wb_mux (
        .in0(alu_out),
        .in1(mem_read_data),
        .sel(MemToReg),
        .out(wb_data)
    );

endmodule

Pipeline execution/tb/tb_1/core_sc_tb.v
`timescale 1ns/1ns
`include "../../src/core_sc.v"
`include "../../src/adder.v"
`include "../../src/alu_control.v"
`include "../../src/alu.v"
`include "../../src/control.v"
`include "../../src/imm.v"
`include "../../src/inst_mem.v"
`include "../../src/mux.v"
`include "../../src/pc.v"
`include "../../src/reg_file.v"
`include "../../src/branch_unit.v"


module core_sc_tb;

    reg clk;
    reg rst;

    core_sc uut (
        .clk(clk),
        .rst(rst)
    );

    // Clock
    initial begin
        clk = 1'b0;
        forever #10 clk = ~clk;   // 50 MHz
    end

    // Reset and run
    initial begin
        rst = 1'b1;
        #50;
        rst = 1'b0;

        // Run for some cycles
        #1000;
        $finish;
    end

    // Waveform
    initial begin
        $dumpfile("core_sc_waveform.vcd");
        $dumpvars(0, core_sc_tb);
    end

endmodule

Pipeline execution/tb/tb_1/core_sc_waveform.vcd
$date
	Wed Nov 26 06:19:31 2025
$end
$version
	Icarus Verilog
$end
$timescale
	1ns
$end
$scope module core_sc_tb $end
$var reg 1 ! clk $end
$var reg 1 " rst $end
$scope module uut $end
$var wire 2 # ALUOp [1:0] $end
$var wire 1 $ ALUSrc $end
$var wire 1 % Branch $end
$var wire 1 & MemRead $end
$var wire 1 ' MemToReg $end
$var wire 1 ( MemWrite $end
$var wire 1 ) RegWrite $end
$var wire 32 * alu_b_in [31:0] $end
$var wire 4 + alu_ctrl [3:0] $end
$var wire 32 , alu_out [31:0] $end
$var wire 1 - clk $end
$var wire 8 . data_word_addr [7:0] $end
$var wire 3 / funct3 [2:0] $end
$var wire 1 0 funct7_5 $end
$var wire 32 1 imm_out [31:0] $end
$var wire 32 2 instr [31:0] $end
$var wire 32 3 mem_read_data [31:0] $end
$var wire 7 4 opcode [6:0] $end
$var wire 32 5 pc_branch [31:0] $end
$var wire 32 6 pc_curr [31:0] $end
$var wire 32 7 pc_next [31:0] $end
$var wire 32 8 pc_plus4 [31:0] $end
$var wire 5 9 rd [4:0] $end
$var wire 5 : rs1 [4:0] $end
$var wire 32 ; rs1_data [31:0] $end
$var wire 5 < rs2 [4:0] $end
$var wire 32 = rs2_data [31:0] $end
$var wire 1 > rst $end
$var wire 1 ? take_branch $end
$var wire 32 @ wb_data [31:0] $end
$var wire 1 A zero $end
$var integer 32 B i [31:0] $end
$scope module u_pc $end
$var wire 1 - clk $end
$var wire 32 C pc_in [31:0] $end
$var wire 1 > rst $end
$var reg 32 D pc_out [31:0] $end
$upscope $end
$scope module u_pc_plus4 $end
$var wire 32 E a [31:0] $end
$var wire 32 F b [31:0] $end
$var wire 32 G sum [31:0] $end
$upscope $end
$scope module u_branch_adder $end
$var wire 32 H a [31:0] $end
$var wire 32 I b [31:0] $end
$var wire 32 J sum [31:0] $end
$upscope $end
$scope module u_pc_mux $end
$var wire 32 K in0 [31:0] $end
$var wire 32 L in1 [31:0] $end
$var wire 1 ? sel $end
$var reg 32 M out [31:0] $end
$upscope $end
$scope module u_imem $end
$var wire 32 N instruction_out [31:0] $end
$var wire 32 O read_address [31:0] $end
$var wire 8 P word_addr [7:0] $end
$upscope $end
$scope module u_regfile $end
$var wire 5 Q Rd [4:0] $end
$var wire 1 ) RegWrite $end
$var wire 5 R Rs1 [4:0] $end
$var wire 5 S Rs2 [4:0] $end
$var wire 32 T Write_data [31:0] $end
$var wire 1 - clk $end
$var wire 32 U read_data1 [31:0] $end
$var wire 32 V read_data2 [31:0] $end
$var wire 1 > rst $end
$var integer 32 W i [31:0] $end
$upscope $end
$scope module u_ctrl $end
$var wire 7 X opcode [6:0] $end
$var reg 2 Y ALUOp [1:0] $end
$var reg 1 Z ALUSrc $end
$var reg 1 [ Branch $end
$var reg 1 \ MemRead $end
$var reg 1 ] MemToReg $end
$var reg 1 ^ MemWrite $end
$var reg 1 _ RegWrite $end
$upscope $end
$scope module u_imm $end
$var wire 32 ` instruction [31:0] $end
$var wire 7 a opcode [6:0] $end
$var reg 32 b imm_out [31:0] $end
$upscope $end
$scope module u_alu_ctrl $end
$var wire 2 c ALUOp [1:0] $end
$var wire 3 d funct3 [2:0] $end
$var wire 1 0 funct7_5 $end
$var reg 4 e ALUCtrl [3:0] $end
$upscope $end
$scope module u_alusrc_mux $end
$var wire 32 f in0 [31:0] $end
$var wire 32 g in1 [31:0] $end
$var wire 1 $ sel $end
$var reg 32 h out [31:0] $end
$upscope $end
$scope module u_alu $end
$var wire 32 i A [31:0] $end
$var wire 32 j B [31:0] $end
$var wire 4 k alu_ctrl [3:0] $end
$var reg 32 l alu_out [31:0] $end
$var reg 1 m zero $end
$upscope $end
$scope module u_wb_mux $end
$var wire 32 n in0 [31:0] $end
$var wire 32 o in1 [31:0] $end
$var wire 1 ' sel $end
$var reg 32 p out [31:0] $end
$upscope $end
$upscope $end
$upscope $end
$enddefinitions $end
#0
$dumpvars
bx p
bx o
bx n
xm
bx l
b0 k
bx j
bx i
bx h
b0 g
bx f
b0 e
bx d
b0 c
b0 b
bx a
bx `
0_
0^
0]
0\
0[
0Z
b0 Y
bx X
bx W
bx V
bx U
bx T
bx S
bx R
bx Q
bx P
bx O
bx N
bx M
bx L
bx K
bx J
b0 I
bx H
bx G
b100 F
bx E
bx D
bx C
bx B
xA
bx @
0?
1>
bx =
bx <
bx ;
bx :
bx 9
bx 8
bx 7
bx 6
bx 5
bx 4
bx 3
bx 2
b0 1
x0
bx /
bx .
0-
bx ,
b0 +
bx *
0)
0(
0'
0&
0%
0$
b0 #
1"
0!
$end
#10
1Z
1$
1_
1)
b10 Y
b10 #
b10 c
b0 3
b0 o
b0 .
b0 p
b0 @
b0 T
1m
1A
b0 l
b0 ,
b0 n
b0 h
b0 *
b0 j
b0 =
b0 V
b0 f
b0 ;
b0 U
b0 i
b10011 a
00
b0 <
b0 S
b0 :
b0 R
b0 /
b0 d
b1 9
b1 Q
b10011 4
b10011 X
b100 M
b100 7
b100 C
b10010011 2
b10010011 N
b10010011 `
b0 P
b0 D
b100 8
b100 G
b100 K
b0 5
b0 J
b0 L
b0 6
b0 E
b0 H
b0 O
b100000 W
b100000000 B
1!
1-
#20
0!
0-
#30
b100000000 B
b100000 W
1!
1-
#40
0!
0-
#50
b1 .
b100 p
b100 @
b100 T
0m
0A
b100 l
b100 ,
b100 n
b100 h
b100 *
b100 j
b100 <
b100 S
b10 9
b10 Q
b100 b
b100 1
b100 I
b100 g
b1000 M
b1000 7
b1000 C
b10000000000000100010011 2
b10000000000000100010011 N
b10000000000000100010011 `
b1 P
b100 D
b1000 8
b1000 G
b1000 K
b1000 5
b1000 J
b1000 L
b100 6
b100 E
b100 H
b100 O
1!
1-
0"
0>
#60
0!
0-
#70
0Z
0$
0m
0A
b1 .
b100 p
b100 @
b100 T
b100 l
b100 ,
b100 n
b100 =
b100 V
b100 f
b100 h
b100 *
b100 j
b110011 a
b10 <
b10 S
b1 :
b1 R
b100 9
b100 Q
b110011 4
b110011 X
b0 b
b0 1
b0 I
b0 g
b1100 M
b1100 7
b1100 C
b1000001000001000110011 2
b1000001000001000110011 N
b1000001000001000110011 `
b10 P
b1000 D
b1100 8
b1100 G
b1100 K
b1000 5
b1000 J
b1000 L
b1000 6
b1000 E
b1000 H
b1000 O
1!
1-
#80
0!
0-
#90
b0 h
b0 *
b0 j
1Z
1$
0_
0)
1^
1(
b0 Y
b0 #
b0 c
b1 .
b100 p
b100 @
b100 T
0m
0A
b100 l
b100 ,
b100 n
b100 ;
b100 U
b100 i
b0 e
b0 +
b0 k
b100011 a
b100 <
b100 S
b10 :
b10 R
b10 /
b10 d
b0 9
b0 Q
b100011 4
b100011 X
b10000 M
b10000 7
b10000 C
b10000010010000000100011 2
b10000010010000000100011 N
b10000010010000000100011 `
b11 P
b1100 D
b10000 8
b10000 G
b10000 K
b1100 5
b1100 J
b1100 L
b1100 6
b1100 E
b1100 H
b1100 O
1!
1-
#100
0!
0-
#110
1]
1'
1_
1)
1\
1&
0^
0(
b10 .
b0 p
b0 @
b0 T
b1000 l
b1000 ,
b1000 n
b100 h
b100 *
b100 j
b11 a
b101 9
b101 Q
b11 4
b11 X
b100 b
b100 1
b100 I
b100 g
b10100 M
b10100 7
b10100 C
b10000010010001010000011 2
b10000010010001010000011 N
b10000010010001010000011 `
b100 P
b0 3
b0 o
b10000 D
b10100 8
b10100 G
b10100 K
b10100 5
b10100 J
b10100 L
b10000 6
b10000 E
b10000 H
b10000 O
1!
1-
#120
0!
0-
#130
0]
0'
0\
0&
b10 Y
b10 #
b10 c
b101 p
b101 @
b101 T
b100 3
b100 o
b1 .
b101 l
b101 ,
b101 n
b0 =
b0 V
b0 f
b0 ;
b0 U
b0 i
b101 h
b101 *
b101 j
b10011 a
b101 <
b101 S
b0 :
b0 R
b0 /
b0 d
b110 9
b110 Q
b10011 4
b10011 X
b101 b
b101 1
b101 I
b101 g
b11000 M
b11000 7
b11000 C
b10100000000001100010011 2
b10100000000001100010011 N
b10100000000001100010011 `
b101 P
b10100 D
b11000 8
b11000 G
b11000 K
b11001 5
b11001 J
b11001 L
b10100 6
b10100 E
b10100 H
b10100 O
1!
1-
#140
0!
0-
#150
0Z
0$
0_
0)
b0 Y
b0 #
b0 c
bx 3
bx o
bx .
bx p
bx @
bx T
xm
xA
bx l
bx ,
bx n
bx =
bx V
bx f
bx ;
bx U
bx i
bx h
bx *
bx j
bx a
x0
bx <
bx S
bx :
bx R
bx /
bx d
bx 9
bx Q
bx 4
bx X
b0 b
b0 1
b0 I
b0 g
b11100 M
b11100 7
b11100 C
bx 2
bx N
bx `
b110 P
b11000 D
b11100 8
b11100 G
b11100 K
b11000 5
b11000 J
b11000 L
b11000 6
b11000 E
b11000 H
b11000 O
1!
1-
#160
0!
0-
#170
b100000 M
b100000 7
b100000 C
b111 P
b11100 D
b100000 8
b100000 G
b100000 K
b11100 5
b11100 J
b11100 L
b11100 6
b11100 E
b11100 H
b11100 O
1!
1-
#180
0!
0-
#190
b100100 M
b100100 7
b100100 C
b1000 P
b100000 D
b100100 8
b100100 G
b100100 K
b100000 5
b100000 J
b100000 L
b100000 6
b100000 E
b100000 H
b100000 O
1!
1-
#200
0!
0-
#210
b101000 M
b101000 7
b101000 C
b1001 P
b100100 D
b101000 8
b101000 G
b101000 K
b100100 5
b100100 J
b100100 L
b100100 6
b100100 E
b100100 H
b100100 O
1!
1-
#220
0!
0-
#230
b101100 M
b101100 7
b101100 C
b1010 P
b101000 D
b101100 8
b101100 G
b101100 K
b101000 5
b101000 J
b101000 L
b101000 6
b101000 E
b101000 H
b101000 O
1!
1-
#240
0!
0-
#250
b110000 M
b110000 7
b110000 C
b1011 P
b101100 D
b110000 8
b110000 G
b110000 K
b101100 5
b101100 J
b101100 L
b101100 6
b101100 E
b101100 H
b101100 O
1!
1-
#260
0!
0-
#270
b110100 M
b110100 7
b110100 C
b1100 P
b110000 D
b110100 8
b110100 G
b110100 K
b110000 5
b110000 J
b110000 L
b110000 6
b110000 E
b110000 H
b110000 O
1!
1-
#280
0!
0-
#290
b111000 M
b111000 7
b111000 C
b1101 P
b110100 D
b111000 8
b111000 G
b111000 K
b110100 5
b110100 J
b110100 L
b110100 6
b110100 E
b110100 H
b110100 O
1!
1-
#300
0!
0-
#310
b111100 M
b111100 7
b111100 C
b1110 P
b111000 D
b111100 8
b111100 G
b111100 K
b111000 5
b111000 J
b111000 L
b111000 6
b111000 E
b111000 H
b111000 O
1!
1-
#320
0!
0-
#330
b1000000 M
b1000000 7
b1000000 C
b1111 P
b111100 D
b1000000 8
b1000000 G
b1000000 K
b111100 5
b111100 J
b111100 L
b111100 6
b111100 E
b111100 H
b111100 O
1!
1-
#340
0!
0-
#350
b1000100 M
b1000100 7
b1000100 C
b10000 P
b1000000 D
b1000100 8
b1000100 G
b1000100 K
b1000000 5
b1000000 J
b1000000 L
b1000000 6
b1000000 E
b1000000 H
b1000000 O
1!
1-
#360
0!
0-
#370
b1001000 M
b1001000 7
b1001000 C
b10001 P
b1000100 D
b1001000 8
b1001000 G
b1001000 K
b1000100 5
b1000100 J
b1000100 L
b1000100 6
b1000100 E
b1000100 H
b1000100 O
1!
1-
#380
0!
0-
#390
b1001100 M
b1001100 7
b1001100 C
b10010 P
b1001000 D
b1001100 8
b1001100 G
b1001100 K
b1001000 5
b1001000 J
b1001000 L
b1001000 6
b1001000 E
b1001000 H
b1001000 O
1!
1-
#400
0!
0-
#410
b1010000 M
b1010000 7
b1010000 C
b10011 P
b1001100 D
b1010000 8
b1010000 G
b1010000 K
b1001100 5
b1001100 J
b1001100 L
b1001100 6
b1001100 E
b1001100 H
b1001100 O
1!
1-
#420
0!
0-
#430
b1010100 M
b1010100 7
b1010100 C
b10100 P
b1010000 D
b1010100 8
b1010100 G
b1010100 K
b1010000 5
b1010000 J
b1010000 L
b1010000 6
b1010000 E
b1010000 H
b1010000 O
1!
1-
#440
0!
0-
#450
b1011000 M
b1011000 7
b1011000 C
b10101 P
b1010100 D
b1011000 8
b1011000 G
b1011000 K
b1010100 5
b1010100 J
b1010100 L
b1010100 6
b1010100 E
b1010100 H
b1010100 O
1!
1-
#460
0!
0-
#470
b1011100 M
b1011100 7
b1011100 C
b10110 P
b1011000 D
b1011100 8
b1011100 G
b1011100 K
b1011000 5
b1011000 J
b1011000 L
b1011000 6
b1011000 E
b1011000 H
b1011000 O
1!
1-
#480
0!
0-
#490
b1100000 M
b1100000 7
b1100000 C
b10111 P
b1011100 D
b1100000 8
b1100000 G
b1100000 K
b1011100 5
b1011100 J
b1011100 L
b1011100 6
b1011100 E
b1011100 H
b1011100 O
1!
1-
#500
0!
0-
#510
b1100100 M
b1100100 7
b1100100 C
b11000 P
b1100000 D
b1100100 8
b1100100 G
b1100100 K
b1100000 5
b1100000 J
b1100000 L
b1100000 6
b1100000 E
b1100000 H
b1100000 O
1!
1-
#520
0!
0-
#530
b1101000 M
b1101000 7
b1101000 C
b11001 P
b1100100 D
b1101000 8
b1101000 G
b1101000 K
b1100100 5
b1100100 J
b1100100 L
b1100100 6
b1100100 E
b1100100 H
b1100100 O
1!
1-
#540
0!
0-
#550
b1101100 M
b1101100 7
b1101100 C
b11010 P
b1101000 D
b1101100 8
b1101100 G
b1101100 K
b1101000 5
b1101000 J
b1101000 L
b1101000 6
b1101000 E
b1101000 H
b1101000 O
1!
1-
#560
0!
0-
#570
b1110000 M
b1110000 7
b1110000 C
b11011 P
b1101100 D
b1110000 8
b1110000 G
b1110000 K
b1101100 5
b1101100 J
b1101100 L
b1101100 6
b1101100 E
b1101100 H
b1101100 O
1!
1-
#580
0!
0-
#590
b1110100 M
b1110100 7
b1110100 C
b11100 P
b1110000 D
b1110100 8
b1110100 G
b1110100 K
b1110000 5
b1110000 J
b1110000 L
b1110000 6
b1110000 E
b1110000 H
b1110000 O
1!
1-
#600
0!
0-
#610
b1111000 M
b1111000 7
b1111000 C
b11101 P
b1110100 D
b1111000 8
b1111000 G
b1111000 K
b1110100 5
b1110100 J
b1110100 L
b1110100 6
b1110100 E
b1110100 H
b1110100 O
1!
1-
#620
0!
0-
#630
b1111100 M
b1111100 7
b1111100 C
b11110 P
b1111000 D
b1111100 8
b1111100 G
b1111100 K
b1111000 5
b1111000 J
b1111000 L
b1111000 6
b1111000 E
b1111000 H
b1111000 O
1!
1-
#640
0!
0-
#650
b10000000 M
b10000000 7
b10000000 C
b11111 P
b1111100 D
b10000000 8
b10000000 G
b10000000 K
b1111100 5
b1111100 J
b1111100 L
b1111100 6
b1111100 E
b1111100 H
b1111100 O
1!
1-
#660
0!
0-
#670
b10000100 M
b10000100 7
b10000100 C
b100000 P
b10000000 D
b10000100 8
b10000100 G
b10000100 K
b10000000 5
b10000000 J
b10000000 L
b10000000 6
b10000000 E
b10000000 H
b10000000 O
1!
1-
#680
0!
0-
#690
b10001000 M
b10001000 7
b10001000 C
b100001 P
b10000100 D
b10001000 8
b10001000 G
b10001000 K
b10000100 5
b10000100 J
b10000100 L
b10000100 6
b10000100 E
b10000100 H
b10000100 O
1!
1-
#700
0!
0-
#710
b10001100 M
b10001100 7
b10001100 C
b100010 P
b10001000 D
b10001100 8
b10001100 G
b10001100 K
b10001000 5
b10001000 J
b10001000 L
b10001000 6
b10001000 E
b10001000 H
b10001000 O
1!
1-
#720
0!
0-
