Single Cycle/src/alu.v
module alu (
    input [31:0] A,B,
    input [3:0] alu_ctrl,
    output reg [31:0] alu_out,
    output reg zero
);
    always @(*) begin
        case (alu_ctrl)
            4'd0: alu_out = A + B; //Add
            4'd1: alu_out = A - B; // Substract
            4'd2: alu_out = A & B; //AND
            4'd3: alu_out = A | B; // OR
            4'd4: alu_out = A ^ B; // XOR
            4'd5: alu_out = A << B[4:0]; //SLL
            4'd6: alu_out = A >> B[4:0]; //SRL
            4'd7: alu_out = $signed(A) >>> B[4:0]; //SRA
            4'd8: alu_out = $signed(A) < $signed(B) ? 32'b1 :32'b0; //SLT signed
            4'd9: alu_out = (A < B) ? 32'b1 : 32'b0;
            4'd10: alu_out = B; // PASS B (for LUI, if you decide to use ALU)                               
            default: alu_out = A + B;
        endcase
        zero = (alu_out == 32'b0);
    end
endmodule

Single Cycle/tb/modules testbench/alu_tb.v
`timescale 1ns/1ns
`include "../../src/alu.v"

module alu_tb;

    reg  [31:0] A, B;
    reg  [3:0]  alu_ctrl;
    wire [31:0] alu_out;
    wire        zero;

    alu uut (
        .A        (A),
        .B        (B),
        .alu_ctrl (alu_ctrl),
        .alu_out  (alu_out),
        .zero     (zero)
    );

    // simple task for one test case
    task run_case;
        input [3:0]  ctrl;
        input [31:0] a_in, b_in;
        input [31:0] exp_out;
        input        exp_zero;
    begin
        A        = a_in;
        B        = b_in;
        alu_ctrl = ctrl;
        #10; // let combinational logic settle

        if (alu_out === exp_out && zero === exp_zero)
            $display("PASS: ctrl=%0d A=%h B=%h -> out=%h zero=%b",
                     ctrl, a_in, b_in, alu_out, zero);
        else begin
            $display("FAIL: ctrl=%0d A=%h B=%h -> out=%h zero=%b (exp %h %b)",
                     ctrl, a_in, b_in, alu_out, zero, exp_out, exp_zero);
        end
    end
    endtask

    initial begin
        $dumpfile("alu_waveform.vcd");
        $dumpvars(0, alu_tb);

        // initialize
        A = 0; B = 0; alu_ctrl = 0;
        #5;

        // ADD
        run_case(4'd0, 32'd10, 32'd5,  32'd15, 1'b0);

        // SUB
        run_case(4'd1, 32'd10, 32'd10, 32'd0,  1'b1);

        // AND
        run_case(4'd2, 32'hffff0000, 32'h0f0f0f0f, 32'h0f0f0000, 1'b0);

        // OR
        run_case(4'd3, 32'h0000ffff, 32'hf0f0f0f0, 32'hf0f0ffff, 1'b0);

        // XOR
        run_case(4'd4, 32'hff00ff00, 32'h0f0f0f0f, 32'hf00ff00f, 1'b0);

        // SLL
        run_case(4'd5, 32'h00000001, 32'd4,        32'h00000010, 1'b0);

        // SRL
        run_case(4'd6, 32'h00000080, 32'd4,        32'h00000008, 1'b0);

        // SRA (signed)
        run_case(4'd7, 32'hfffffff0, 32'd2,        32'hfffffffc, 1'b0);

        // SLT (signed)
        run_case(4'd8, -32'sd1,      32'sd5,       32'd1,        1'b0);
        run_case(4'd8,  32'sd10,     32'sd5,       32'd0,        1'b1);

        // SLTU (unsigned)
        run_case(4'd9, 32'h00000001, 32'hffffffff, 32'd1,        1'b0);
        run_case(4'd9, 32'hffffffff, 32'h00000001, 32'd0,        1'b1);

        // PASS_B
        run_case(4'd10, 32'h12345678, 32'hdeadbeef, 32'hdeadbeef, 1'b0);

        #10;
        $finish;
    end

endmodule

Single Cycle/tb/modules testbench/alu_waveform.vcd
$date
	Wed Nov 26 04:47:08 2025
$end
$version
	Icarus Verilog
$end
$timescale
	1ns
$end
$scope module alu_tb $end
$var wire 32 ! alu_out [31:0] $end
$var wire 1 " zero $end
$var reg 32 # A [31:0] $end
$var reg 32 $ B [31:0] $end
$var reg 4 % alu_ctrl [3:0] $end
$scope module uut $end
$var wire 32 & A [31:0] $end
$var wire 32 ' B [31:0] $end
$var wire 4 ( alu_ctrl [3:0] $end
$var reg 32 ) alu_out [31:0] $end
$var reg 1 * zero $end
$upscope $end
$scope task run_case $end
$var reg 32 + a_in [31:0] $end
$var reg 32 , b_in [31:0] $end
$var reg 4 - ctrl [3:0] $end
$var reg 32 . exp_out [31:0] $end
$var reg 1 / exp_zero $end
$upscope $end
$upscope $end
$enddefinitions $end
#0
$dumpvars
x/
bx .
bx -
bx ,
bx +
1*
b0 )
b0 (
b0 '
b0 &
b0 %
b0 $
b0 #
1"
b0 !
$end
#5
0*
0"
b1111 )
b1111 !
b101 $
b101 '
b1010 #
b1010 &
0/
b1111 .
b101 ,
b1010 +
b0 -
#15
1*
1"
b0 )
b0 !
b1 %
b1 (
b1010 $
b1010 '
1/
b0 .
b1010 ,
b1 -
#25
0*
0"
b1111000011110000000000000000 )
b1111000011110000000000000000 !
b10 %
b10 (
b1111000011110000111100001111 $
b1111000011110000111100001111 '
b11111111111111110000000000000000 #
b11111111111111110000000000000000 &
0/
b1111000011110000000000000000 .
b1111000011110000111100001111 ,
b11111111111111110000000000000000 +
b10 -
#35
b11110000111100001111111111111111 )
b11110000111100001111111111111111 !
b11 %
b11 (
b11110000111100001111000011110000 $
b11110000111100001111000011110000 '
b1111111111111111 #
b1111111111111111 &
b11110000111100001111111111111111 .
b11110000111100001111000011110000 ,
b1111111111111111 +
b11 -
#45
b11110000000011111111000000001111 )
b11110000000011111111000000001111 !
b100 %
b100 (
b1111000011110000111100001111 $
b1111000011110000111100001111 '
b11111111000000001111111100000000 #
b11111111000000001111111100000000 &
b11110000000011111111000000001111 .
b1111000011110000111100001111 ,
b11111111000000001111111100000000 +
b100 -
#55
b10000 )
b10000 !
b101 %
b101 (
b100 $
b100 '
b1 #
b1 &
b10000 .
b100 ,
b1 +
b101 -
#65
b1000 )
b1000 !
b110 %
b110 (
b10000000 #
b10000000 &
b1000 .
b10000000 +
b110 -
#75
b11111111111111111111111111111100 )
b11111111111111111111111111111100 !
b111 %
b111 (
b10 $
b10 '
b11111111111111111111111111110000 #
b11111111111111111111111111110000 &
b11111111111111111111111111111100 .
b10 ,
b11111111111111111111111111110000 +
b111 -
#85
b1 )
b1 !
b1000 %
b1000 (
b101 $
b101 '
b11111111111111111111111111111111 #
b11111111111111111111111111111111 &
b1 .
b101 ,
b11111111111111111111111111111111 +
b1000 -
#95
1*
1"
b0 )
b0 !
b1010 #
b1010 &
1/
b0 .
b1010 +
#105
0*
0"
b1 )
b1 !
b1001 %
b1001 (
b11111111111111111111111111111111 $
b11111111111111111111111111111111 '
b1 #
b1 &
0/
b1 .
b11111111111111111111111111111111 ,
b1 +
b1001 -
#115
1*
1"
b0 )
b0 !
b1 $
b1 '
b11111111111111111111111111111111 #
b11111111111111111111111111111111 &
1/
b0 .
b1 ,
b11111111111111111111111111111111 +
#125
0*
0"
b11011110101011011011111011101111 )
b11011110101011011011111011101111 !
b1010 %
b1010 (
b11011110101011011011111011101111 $
b11011110101011011011111011101111 '
b10010001101000101011001111000 #
b10010001101000101011001111000 &
0/
b11011110101011011011111011101111 .
b11011110101011011011111011101111 ,
b10010001101000101011001111000 +
b1010 -
