src/modules/alu_control.v
module alu_control(
    input  [1:0] ALUOp,
    input  [2:0] funct3,
    input        funct7_5,      // instruction[30]
    output reg [3:0] ALUCtrl
);

always @(*) begin
    case (ALUOp)
        2'b00: ALUCtrl = 4'b0000;              // ADD (load/store, auipc)
        2'b01: ALUCtrl = 4'b0001;              // SUB (branches)

        2'b10: begin                           // R / I-type ALU ops
            case ({funct7_5, funct3})
                4'b0_000: ALUCtrl = 4'b0000;   // ADD / ADDI
                4'b1_000: ALUCtrl = 4'b0001;   // SUB
                4'b0_111: ALUCtrl = 4'b0010;   // AND / ANDI
                4'b0_110: ALUCtrl = 4'b0011;   // OR / ORI
                4'b0_100: ALUCtrl = 4'b0100;   // XOR / XORI
                4'b0_001: ALUCtrl = 4'b0101;   // SLL / SLLI
                4'b0_101: ALUCtrl = 4'b0110;   // SRL / SRLI
                4'b1_101: ALUCtrl = 4'b0111;   // SRA / SRAI
                4'b0_010: ALUCtrl = 4'b1000;   // SLT / SLTI
                4'b0_011: ALUCtrl = 4'b1001;   // SLTU / SLTIU
                default:  ALUCtrl = 4'b0000;
            endcase
        end

        2'b11: begin
            // Special ALUOp for LUI (and only LUI)
            ALUCtrl = 4'b1010;                 // PASS B (alu_out = B = imm_out)
        end

        default: ALUCtrl = 4'b0000;
    endcase
end

endmodule

tb/modules testbench/alu_control_tb.v
`timescale 1ns/1ns
`include "../../src/alu_control.v"

module alu_control_tb;

    reg  [1:0] ALUOp;
    reg  [2:0] funct3;
    reg        funct7_5;
    wire [3:0] ALUCtrl;

    alu_control dut (
        .ALUOp   (ALUOp),
        .funct3  (funct3),
        .funct7_5(funct7_5),
        .ALUCtrl (ALUCtrl)
    );

    task run_case;
        input [1:0] ALUOp_in;
        input [2:0] funct3_in;
        input       funct7_5_in;
        input [3:0] exp_ctrl;
    begin
        ALUOp    = ALUOp_in;
        funct3   = funct3_in;
        funct7_5 = funct7_5_in;
        #1;
        if (ALUCtrl === exp_ctrl)
            $display("PASS: ALUOp=%b funct7_5=%b funct3=%b -> %b",
                     ALUOp_in, funct7_5_in, funct3_in, ALUCtrl);
        else
            $display("FAIL: ALUOp=%b funct7_5=%b funct3=%b -> %b exp=%b",
                     ALUOp_in, funct7_5_in, funct3_in, ALUCtrl, exp_ctrl);
    end
    endtask

    initial begin
        $dumpfile("alu_control_waveform.vcd");
        $dumpvars(0, alu_control_tb);

        // ALUOp = 00 (load/store/auipc): ADD
        run_case(2'b00, 3'b000, 1'b0, 4'b0000);

        // ALUOp = 01 (branches): SUB
        run_case(2'b01, 3'b000, 1'b0, 4'b0001);

        // ALUOp = 10, R/I-type:
        run_case(2'b10, 3'b000, 1'b0, 4'b0000); // ADD/ADDI
        run_case(2'b10, 3'b000, 1'b1, 4'b0001); // SUB
        run_case(2'b10, 3'b111, 1'b0, 4'b0010); // AND
        run_case(2'b10, 3'b110, 1'b0, 4'b0011); // OR
        run_case(2'b10, 3'b100, 1'b0, 4'b0100); // XOR
        run_case(2'b10, 3'b001, 1'b0, 4'b0101); // SLL
        run_case(2'b10, 3'b101, 1'b0, 4'b0110); // SRL
        run_case(2'b10, 3'b101, 1'b1, 4'b0111); // SRA
        run_case(2'b10, 3'b010, 1'b0, 4'b1000); // SLT
        run_case(2'b10, 3'b011, 1'b0, 4'b1001); // SLTU

        // ALUOp = 11: LUI => PASS B (ctrl=1010)
        run_case(2'b11, 3'b000, 1'b0, 4'b1010);

        #5;
        $finish;
    end

endmodule

SingleCycle/tb/modules testbench/alu_control_waveform.vcd
$date
	Wed Nov 26 05:15:32 2025
$end
$version
	Icarus Verilog
$end
$timescale
	1ns
$end
$scope module alu_control_tb $end
$var wire 4 ! ALUCtrl [3:0] $end
$var reg 2 " ALUOp [1:0] $end
$var reg 3 # funct3 [2:0] $end
$var reg 1 $ funct7_5 $end
$scope module dut $end
$var wire 2 % ALUOp [1:0] $end
$var wire 3 & funct3 [2:0] $end
$var wire 1 ' funct7_5 $end
$var reg 4 ( ALUCtrl [3:0] $end
$upscope $end
$scope task run_case $end
$var reg 2 ) ALUOp_in [1:0] $end
$var reg 4 * exp_ctrl [3:0] $end
$var reg 3 + funct3_in [2:0] $end
$var reg 1 , funct7_5_in $end
$upscope $end
$upscope $end
$enddefinitions $end
#0
$dumpvars
0,
b0 +
b0 *
b0 )
b0 (
0'
b0 &
b0 %
0$
b0 #
b0 "
b0 !
$end
#1
b1 (
b1 !
b1 "
b1 %
b1 *
b1 )
#2
b0 (
b0 !
b10 "
b10 %
b0 *
b10 )
#3
b1 (
b1 !
1$
1'
b1 *
1,
#4
b10 (
b10 !
0$
0'
b111 #
b111 &
b10 *
0,
b111 +
#5
b11 (
b11 !
b110 #
b110 &
b11 *
b110 +
#6
b100 (
b100 !
b100 #
b100 &
b100 *
b100 +
#7
b101 (
b101 !
b1 #
b1 &
b101 *
b1 +
#8
b110 (
b110 !
b101 #
b101 &
b110 *
b101 +
#9
b111 (
b111 !
1$
1'
b111 *
1,
#10
b1000 (
b1000 !
0$
0'
b10 #
b10 &
b1000 *
0,
b10 +
#11
b1001 (
b1001 !
b11 #
b11 &
b1001 *
b11 +
#12
b1010 (
b1010 !
b0 #
b0 &
b11 "
b11 %
b1010 *
b0 +
b11 )
