Single Cycle/src/inst_mem.v
module inst_mem(
    input  [31:0] read_address,   // PC (byte address)
    output [31:0] instruction_out
);
    reg [31:0] I_Mem [0:255];     // 256 instructions

    wire [7:0] word_addr = read_address[9:2];

    assign instruction_out = I_Mem[word_addr];

    initial begin
        $readmemh("instruction.mem", I_Mem);
    end
endmodule

Single Cycle/tb/modules testbench/inst_mem_tb.v
`timescale 1ns/1ns
`include "../../src/inst_mem.v"   

module inst_mem_tb;

    reg  [31:0] read_address;
    wire [31:0] instruction_out;

    inst_mem dut (
        .read_address   (read_address),
        .instruction_out(instruction_out)
    );

    task run_case;
        input [31:0] addr;
        input [31:0] exp_instr;
    begin
        read_address = addr;
        #1;  // allow combinational read to settle

        if (instruction_out === exp_instr)
            $display("PASS: addr=%0d (0x%08h) -> instr=%08h",
                     addr, addr, instruction_out);
        else
            $display("FAIL: addr=%0d (0x%08h) -> instr=%08h exp=%08h",
                     addr, addr, instruction_out, exp_instr);
    end
    endtask

    initial begin
        $dumpfile("inst_mem_waveform.vcd");
        $dumpvars(0, inst_mem_tb);

        // Small delay to let $readmemh complete
        #1;

        // instruction.mem contents:
        // 0: 00000093
        // 1: 00400113
        // 2: 00208233
        // 3: 00412023
        // 4: 00412283
        // 5: 002102B3
        // 6: 00500313
        // 7: 006283B3
        // 8: 00712423
        // 9: 00812503

        run_case(32'd0,  32'h0000_0093);
        run_case(32'd4,  32'h0040_0113);
        run_case(32'd8,  32'h0020_8233);
        run_case(32'd12, 32'h0041_2023);
        run_case(32'd16, 32'h0041_2283);
        run_case(32'd20, 32'h0021_02b3);
        run_case(32'd24, 32'h0050_0313);
        run_case(32'd28, 32'h0062_83b3);
        run_case(32'd32, 32'h0071_2423);
        run_case(32'd36, 32'h0081_2503);

        // Optional: read some unused location
        run_case(32'd40, 32'hxxxx_xxxx); // expect X / uninitialized

        #5;
        $finish;
    end

endmodule

SingleCycle/tb/modules testbench/inst_mem_waveform.vcd
$date
	Wed Nov 26 05:27:38 2025
$end
$version
	Icarus Verilog
$end
$timescale
	1ns
$end
$scope module inst_mem_tb $end
$var wire 32 ! instruction_out [31:0] $end
$var reg 32 " read_address [31:0] $end
$scope module dut $end
$var wire 32 # instruction_out [31:0] $end
$var wire 32 $ read_address [31:0] $end
$var wire 8 % word_addr [7:0] $end
$upscope $end
$scope task run_case $end
$var reg 32 & addr [31:0] $end
$var reg 32 ' exp_instr [31:0] $end
$upscope $end
$upscope $end
$enddefinitions $end
#0
$dumpvars
bx '
bx &
bx %
bx $
bx #
bx "
bx !
$end
#1
b10010011 !
b10010011 #
b0 %
b0 "
b0 $
b10010011 '
b0 &
#2
b10000000000000100010011 !
b10000000000000100010011 #
b1 %
b100 "
b100 $
b10000000000000100010011 '
b100 &
#3
b1000001000001000110011 !
b1000001000001000110011 #
b10 %
b1000 "
b1000 $
b1000001000001000110011 '
b1000 &
#4
b10000010010000000100011 !
b10000010010000000100011 #
b11 %
b1100 "
b1100 $
b10000010010000000100011 '
b1100 &
#5
b10000010010001010000011 !
b10000010010001010000011 #
b100 %
b10000 "
b10000 $
b10000010010001010000011 '
b10000 &
#6
b1000010000001010110011 !
b1000010000001010110011 #
b101 %
b10100 "
b10100 $
b1000010000001010110011 '
b10100 &
#7
b10100000000001100010011 !
b10100000000001100010011 #
b110 %
b11000 "
b11000 $
b10100000000001100010011 '
b11000 &
#8
b11000101000001110110011 !
b11000101000001110110011 #
b111 %
b11100 "
b11100 $
b11000101000001110110011 '
b11100 &
#9
b11100010010010000100011 !
b11100010010010000100011 #
b1000 %
b100000 "
b100000 $
b11100010010010000100011 '
b100000 &
#10
b100000010010010100000011 !
b100000010010010100000011 #
b1001 %
b100100 "
b100100 $
b100000010010010100000011 '
b100100 &
#11
bx !
bx #
b1010 %
b101000 "
b101000 $
bx '
b101000 &
