src/control.v
module control(
    input [6:0] opcode,          
    output reg RegWrite,         
    output reg MemRead,          
    output reg MemWrite,         
    output reg MemToReg,        
    output reg ALUSrc,                      
    output reg Branch,                        
    output reg [1:0] ALUOp       
);

    always @(*) begin
        case (opcode)
            7'b0110011:  // R-type 
            begin  {ALUSrc, MemToReg, RegWrite, MemRead, MemWrite, Branch, ALUOp} <= {1'b0, 1'b0, 1'b1, 1'b0, 1'b0, 1'b0, 2'b10};end
            7'b0010011:   // I-type
            begin {ALUSrc, MemToReg, RegWrite, MemRead, MemWrite, Branch, ALUOp} <= {1'b1, 1'b0, 1'b1, 1'b0, 1'b0, 1'b0, 2'b10};end
            7'b0000011:   // Load 
            begin {ALUSrc, MemToReg, RegWrite, MemRead, MemWrite, Branch, ALUOp} <= {1'b1, 1'b1, 1'b1, 1'b1, 1'b0, 1'b0, 2'b00};end
            7'b0100011:   // Store 
            begin {ALUSrc, MemToReg, RegWrite, MemRead, MemWrite, Branch, ALUOp} <= {1'b1, 1'b0, 1'b0, 1'b0, 1'b1, 1'b0, 2'b00};end
            7'b1100011:   // Branch 
            begin {ALUSrc, MemToReg, RegWrite, MemRead, MemWrite, Branch, ALUOp} <= {1'b0, 1'b0, 1'b0, 1'b0, 1'b0, 1'b1, 2'b11};end  
            7'b1101111:   // Jump 
            begin  {ALUSrc, MemToReg, RegWrite, MemRead, MemWrite, Branch, ALUOp} <= {1'b0, 1'b0, 1'b1, 1'b0, 1'b0, 1'b0, 2'b10};end
            7'b0110111:   // LUI
            begin {ALUSrc, MemToReg, RegWrite, MemRead, MemWrite, Branch, ALUOp} <= {1'b1, 1'b0, 1'b1, 1'b0, 1'b0, 1'b0, 2'b11};end
            default: 
            begin {ALUSrc, MemToReg, RegWrite, MemRead, MemWrite, Branch, ALUOp} <= {1'b0, 1'b0, 1'b0, 1'b0, 1'b0, 1'b0, 2'b00};end  
        endcase
    end

endmodule

SingleCycle/tb/modules testbench/control_tb.v
`timescale 1ns/1ns
`include "../../src/control.v"

module control_tb;

    reg  [6:0] opcode;
    wire RegWrite, MemRead, MemWrite, MemToReg, ALUSrc, Branch;
    wire [1:0] ALUOp;

    control dut (
        .opcode   (opcode),
        .RegWrite (RegWrite),
        .MemRead  (MemRead),
        .MemWrite (MemWrite),
        .MemToReg (MemToReg),
        .ALUSrc   (ALUSrc),
        .Branch   (Branch),
        .ALUOp    (ALUOp)
    );

    // pack all control signals to compare in one go
    task run_case;
        input [6:0] opcode_in;
        input [7:0] exp_ctrl; // {ALUSrc,MemToReg,RegWrite,MemRead,MemWrite,Branch,ALUOp[1:0]}
        reg   [7:0] act_ctrl;
    begin
        opcode = opcode_in;
        #1; // combinational settle

        act_ctrl = {ALUSrc, MemToReg, RegWrite, MemRead, MemWrite, Branch, ALUOp};

        if (act_ctrl === exp_ctrl)
            $display("PASS: opcode=%b ctrl=%b", opcode_in, act_ctrl);
        else
            $display("FAIL: opcode=%b got=%b exp=%b",
                     opcode_in, act_ctrl, exp_ctrl);
    end
    endtask

    initial begin
        $dumpfile("control_waveform.vcd");
        $dumpvars(0, control_tb);

        // R-type: 0110011 -> {0,0,1,0,0,0,10}
        run_case(7'b0110011, 8'b0_0_1_0_0_0_10);

        // I-type: 0010011
        run_case(7'b0010011, 8'b1_0_1_0_0_0_10);

        // Load: 0000011
        run_case(7'b0000011, 8'b1_1_1_1_0_0_00);

        // Store: 0100011
        run_case(7'b0100011, 8'b1_0_0_0_1_0_00);

        // Branch: 1100011
        run_case(7'b1100011, 8'b0_0_0_0_0_1_11);

        // Jump (JAL): 1101111
        run_case(7'b1101111, 8'b0_0_1_0_0_0_10);

        // LUI: 0110111
        run_case(7'b0110111, 8'b1_0_1_0_0_0_11);

        // Default: something unsupported
        run_case(7'b0000000, 8'b0_0_0_0_0_0_00);

        #5;
        $finish;
    end

endmodule

tb/modules testbench/control_waveform.vcd
$date
	Wed Nov 26 05:00:15 2025
$end
$version
	Icarus Verilog
$end
$timescale
	1ns
$end
$scope module control_tb $end
$var wire 2 ! ALUOp [1:0] $end
$var wire 1 " ALUSrc $end
$var wire 1 # Branch $end
$var wire 1 $ MemRead $end
$var wire 1 % MemToReg $end
$var wire 1 & MemWrite $end
$var wire 1 ' RegWrite $end
$var reg 7 ( opcode [6:0] $end
$scope module dut $end
$var wire 7 ) opcode [6:0] $end
$var reg 2 * ALUOp [1:0] $end
$var reg 1 + ALUSrc $end
$var reg 1 , Branch $end
$var reg 1 - MemRead $end
$var reg 1 . MemToReg $end
$var reg 1 / MemWrite $end
$var reg 1 0 RegWrite $end
$upscope $end
$scope task run_case $end
$var reg 8 1 act_ctrl [7:0] $end
$var reg 8 2 exp_ctrl [7:0] $end
$var reg 7 3 opcode_in [6:0] $end
$upscope $end
$upscope $end
$enddefinitions $end
#0
$dumpvars
b110011 3
b100010 2
bx 1
10
0/
0.
0-
0,
0+
b10 *
b110011 )
b110011 (
1'
0&
0%
0$
0#
0"
b10 !
$end
#1
1+
1"
b10011 (
b10011 )
b10100010 2
b10011 3
b100010 1
#2
1.
1%
1-
1$
b0 *
b0 !
b11 (
b11 )
b11110000 2
b11 3
b10100010 1
#3
0.
0%
00
0'
0-
0$
1/
1&
b100011 (
b100011 )
b10001000 2
b100011 3
b11110000 1
#4
0+
0"
0/
0&
1,
1#
b11 *
b11 !
b1100011 (
b1100011 )
b111 2
b1100011 3
b10001000 1
#5
10
1'
0,
0#
b10 *
b10 !
b1101111 (
b1101111 )
b100010 2
b1101111 3
b111 1
#6
1+
1"
b11 *
b11 !
b110111 (
b110111 )
b10100011 2
b110111 3
b100010 1
#7
0+
0"
00
0'
b0 *
b0 !
b0 (
b0 )
b0 2
b0 3
b10100011 1
#8
b0 1
