Single Cycle/rtl/reg_file.v
module reg_file(
    input         clk,
    input         rst,
    input         RegWrite,
    input  [4:0]  Rs1,
    input  [4:0]  Rs2,
    input  [4:0]  Rd,
    input  [31:0] Write_data,
    output [31:0] read_data1,
    output [31:0] read_data2
);

    // 32 registers, each 32-bit
    reg [31:0] Registers [31:0];

    integer i;

    // Optional: initial values (OK for FPGA, not for ASIC)
    initial begin
        Registers[0]  = 32'd0;
        Registers[1]  = 32'd3;
        Registers[2]  = 32'd2;
        Registers[3]  = 32'd12;
        Registers[4]  = 32'd20;
        Registers[5]  = 32'd3;
        Registers[6]  = 32'd44;
        Registers[7]  = 32'd4;
        Registers[8]  = 32'd2;
        Registers[9]  = 32'd1;
        Registers[10] = 32'd23;
        Registers[11] = 32'd4;
        Registers[12] = 32'd90;
        Registers[13] = 32'd10;
        Registers[14] = 32'd20;
        Registers[15] = 32'd30;
        Registers[16] = 32'd40;
        Registers[17] = 32'd50;
        Registers[18] = 32'd60;
        Registers[19] = 32'd70;
        Registers[20] = 32'd80;
        Registers[21] = 32'd80;
        Registers[22] = 32'd90;
        Registers[23] = 32'd70;
        Registers[24] = 32'd60;
        Registers[25] = 32'd65;
        Registers[26] = 32'd4;
        Registers[27] = 32'd32;
        Registers[28] = 32'd12;
        Registers[29] = 32'd34;
        Registers[30] = 32'd5;
        Registers[31] = 32'd10;
    end

    // Synchronous reset + write
    always @(posedge clk) begin
        if (rst) begin
            for (i = 0; i < 32; i = i + 1)
                Registers[i] <= 32'b0;
        end
        else if (RegWrite && (Rd != 5'd0)) begin
            // x0 is read-only zero in RISC-V: ignore writes to x0
            Registers[Rd] <= Write_data;
        end
    end

    // Combinational read ports
    assign read_data1 = (Rs1 == 5'd0) ? 32'b0 : Registers[Rs1];
    assign read_data2 = (Rs2 == 5'd0) ? 32'b0 : Registers[Rs2];

endmodule

Single Cycle/tb/modules testbench/reg_file_tb.v
`timescale 1ns/1ns
`include "../../src/reg_file.v"

module reg_file_tb;

    reg         clk;
    reg         rst;
    reg         RegWrite;
    reg  [4:0]  Rs1, Rs2, Rd;
    reg  [31:0] Write_data;
    wire [31:0] read_data1, read_data2;

    reg_file dut (
        .clk        (clk),
        .rst        (rst),
        .RegWrite   (RegWrite),
        .Rs1        (Rs1),
        .Rs2        (Rs2),
        .Rd         (Rd),
        .Write_data (Write_data),
        .read_data1 (read_data1),
        .read_data2 (read_data2)
    );

    // 10 ns clock
    initial begin
        clk = 0;
        forever #5 clk = ~clk;
    end

    initial begin
        $dumpfile("reg_file_waveform.vcd");
        $dumpvars(0, reg_file_tb);

        // ---- init ----
        rst        = 1'b1;
        RegWrite   = 1'b0;
        Rs1        = 5'd0;
        Rs2        = 5'd0;
        Rd         = 5'd0;
        Write_data = 32'd0;

        // two posedges with reset asserted
        @(posedge clk);
        @(posedge clk);
        rst = 1'b0;    // deassert reset

        // check after reset
        Rs1 = 5'd0;  #1;
        $display("After reset: x0 = %h (expect 00000000)", read_data1);
        Rs1 = 5'd5;  #1;
        $display("After reset: x5 = %h (expect 00000000)", read_data1);

        // ---- write x5 = 0xDEADBEEF ----
        @(posedge clk);
        RegWrite   <= 1'b1;
        Rd         <= 5'd5;
        Write_data <= 32'hdead_beef;

        @(posedge clk);   // write happens here
        RegWrite   <= 1'b0;

        // ---- write x10 = 0x12345678 ----
        @(posedge clk);
        RegWrite   <= 1'b1;
        Rd         <= 5'd10;
        Write_data <= 32'h1234_5678;

        @(posedge clk);   // write happens here
        RegWrite   <= 1'b0;

        // ---- read back and check ----
        Rs1 = 5'd5;   #1;
        if (read_data1 === 32'hdead_beef)
            $display("PASS: x5 = %h", read_data1);
        else
            $display("FAIL: x5 = %h exp=deadbeef", read_data1);

        Rs1 = 5'd10;  #1;
        if (read_data1 === 32'h1234_5678)
            $display("PASS: x10 = %h", read_data1);
        else
            $display("FAIL: x10 = %h exp=12345678", read_data1);

        // ---- try to write x0 (should still be 0) ----
        @(posedge clk);
        RegWrite   <= 1'b1;
        Rd         <= 5'd0;
        Write_data <= 32'hffff_ffff;

        @(posedge clk);
        RegWrite   <= 1'b0;

        Rs1 = 5'd0;  #1;
        if (read_data1 === 32'd0)
            $display("PASS: x0 still = %h", read_data1);
        else
            $display("FAIL: x0 = %h exp=00000000", read_data1);

        #10;
        $finish;
    end

endmodule

tb/modules testbench/reg_file_waveform.vcd
$date
	Wed Nov 26 05:13:34 2025
$end
$version
	Icarus Verilog
$end
$timescale
	1ns
$end
$scope module reg_file_tb $end
$var wire 32 ! read_data1 [31:0] $end
$var wire 32 " read_data2 [31:0] $end
$var reg 5 # Rd [4:0] $end
$var reg 1 $ RegWrite $end
$var reg 5 % Rs1 [4:0] $end
$var reg 5 & Rs2 [4:0] $end
$var reg 32 ' Write_data [31:0] $end
$var reg 1 ( clk $end
$var reg 1 ) rst $end
$scope module dut $end
$var wire 5 * Rd [4:0] $end
$var wire 1 + RegWrite $end
$var wire 5 , Rs1 [4:0] $end
$var wire 5 - Rs2 [4:0] $end
$var wire 32 . Write_data [31:0] $end
$var wire 1 / clk $end
$var wire 32 0 read_data1 [31:0] $end
$var wire 32 1 read_data2 [31:0] $end
$var wire 1 2 rst $end
$var integer 32 3 i [31:0] $end
$upscope $end
$upscope $end
$enddefinitions $end
#0
$dumpvars
bx 3
12
b0 1
b0 0
0/
b0 .
b0 -
b0 ,
0+
b0 *
1)
0(
b0 '
b0 &
b0 %
0$
b0 #
b0 "
b0 !
$end
#5
b100000 3
1(
1/
#10
0(
0/
#15
0)
02
b100000 3
1(
1/
#16
b101 %
b101 ,
#20
0(
0/
#25
b11011110101011011011111011101111 '
b11011110101011011011111011101111 .
b101 #
b101 *
1$
1+
1(
1/
#30
0(
0/
#35
b11011110101011011011111011101111 !
b11011110101011011011111011101111 0
0$
0+
1(
1/
#40
0(
0/
#45
b10010001101000101011001111000 '
b10010001101000101011001111000 .
b1010 #
b1010 *
1$
1+
1(
1/
#50
0(
0/
#55
0$
0+
1(
1/
#56
b10010001101000101011001111000 !
b10010001101000101011001111000 0
b1010 %
b1010 ,
#60
0(
0/
#65
b11111111111111111111111111111111 '
b11111111111111111111111111111111 .
b0 #
b0 *
1$
1+
1(
1/
#70
0(
0/
#75
0$
0+
b0 !
b0 0
b0 %
b0 ,
1(
1/
